Workbook

Sheet Matriz Layout Camara
A1: FAMILIA | B1: Almacen | C1: Rack | D1: Categoría_ID_Actual | E1: ID_ABC | F1: Categoria_ABC | G1: Administracion_Inventario | H1: Color_tarjeta | I1: Ubicación Rack Hoy | J1: Numero de Rack | K1: Nivel | L1: Posicion_numero P[] | M1: Stock_Maximo (Bultos) | N1: Bulto (kg/BULTO) | O1: Total Maximo (kg) | P1: USD en gasto Kwh /Kg anuales | Q1: Volumen m3_Bulto | R1: Kg/m3_bulto | S1: Posiciones_Maximas | T1: USD en gasto Kwh /posicion anuales | U1: Total_VolumenMaximo_Producto (m3 en el espacio de los racks) | V1: Superficie ocupacion_Producto (m2) | W1: Volumen Útil total Disponible Camara (m3 según espacion de racks aire + producto ) | X1: Superfice interna bruta total de la Camara m2 | Y1: %util superficie total camara m2 | Z1: %Utilizacion volumetrica Producto (utilzacion real del volumen de los Racks) | AA1: Volumen interno Bruto Camara (m3) | AB1: % Ocupacion Neto Volumen m3 Racks_(Aire+Producto)_ Total volumen camara | AC1: Prorrateo Kw_h_anual_Rack (Aire+Producto) Camara m3 | AD1: Prorrateo Kw_h_anual_Pasillo_camara m3 | AE1: Total_Kw_h_Producto_m3 | AF1: USD de energia Kwh/m3 | AG1: Kw_h/kg almacenado Producto | AH1: USD de energia Kwh/Kg almacenado | AI1: Prorrateo % _kg_Maximo_almacenables_camara | AJ1: % de Kg vendido al año | AK1: % AR$ Vendido al año | AL1: Monto anual total comprado USD | AM1: Monto semanal comprado promedio USD | AN1: Kw_h anuales | AO1: Costo Kw_h_Anuales_USD | AP1: USD/Kwh (Ultimo) | AQ1: USD energia/ USD Comprado año
A2: GRANEL | B2: CAMARA | C2: =+J2 -> 1 | D2: GRANEL A | E2: Criticos | F2: AAA | G2: Crítico - Alta Rotación y Rentabilidad (Control Diario) | H2: Verde | I2: Izquierda_primer Rack | J2: 1 | K2: ND | L2: ND | M2: 160 | N2: 7.8 | O2: =+N2*S2 -> 1248 | P2: =$AO$3*O2/($O$2+$O$3) -> 5871.9976 | Q2: 0.0104 | R2: =+N2/Q2 -> 750 | S2: 160 | T2: =$AO$3*S2/($S$2+$S$3) -> 5871.9976 | U2: =+Q2*S2 -> 1.664 | V2: 1.62 | W2: 2.71 | X2: 14.21 | Y2: =+V2/X2 -> 0.11400422 | Z2: =+U2/W2 -> 0.61402214 | AA2: 34.104 | AB2: =+W2/AA2 -> 0.07946282 | AC2: =+AB2*AN3 -> 2455.8183 | AD2: =(2.09*2.94*0.75+1.2*1.6*2.09)/AA2*AB2*AN3 -> 620.8135 | AE2: =+AC2+AD2 -> 3076.6318 | AF2: =+AE2*AP3 -> 993.75208 | AG2: =+AE2/O2 -> 2.4652499 | AH2: =+AG2*AP3 -> 0.79627571 | AI2: =+O2/$O$1048576 -> 0.295699
A3: GRANEL | B3: CAMARA | C3: =+J3 -> 5 | D3: GRANEL B | E3: Criticos | F3: AAA | G3: Crítico - Alta Rotación y Rentabilidad (Control Diario) | H3: Verde | I3: Derecha_primer Rack | J3: 5 | K3: ND | L3: ND | M3: 112 | N3: 7.8 | O3: =+N3*S3 -> 873.6 | P3: =$AO$3*O3/($O$2+$O$3) -> 4110.3983 | Q3: =20*20*26/1000000 -> 0.0104 | R3: =+N3/Q3 -> 750 | S3: 112 | T3: =$AO$3*S3/($S$2+$S$3) -> 4110.3983 | U3: =+Q3*S3 -> 1.1648 | V3: 1.05 | W3: 1.85 | X3: 14.21 | Y3: =+V3/X3 -> 0.073891626 | Z3: =+U3/W3 -> 0.62962162 | AA3: =14.21*2.4 -> 34.104 | AB3: =+W3/AA3 -> 0.054245836 | AC3: =+AN3*AB3 -> 1676.4811 | AD3: =(2.09*2.94*0.75+1.2*1.6*2.09)/AA3*AB3*AN3 -> 423.80258 | AE3: =+AC3+AD3 -> 2100.2837 | AF3: =+AE3*AP3 -> 678.39164 | AG3: =+AE3/O3 -> 2.4041709 | AH3: =+AG3*AP3 -> 0.77654721 | AI3: =+O3/$O$1048576 -> 0.2069893 | AJ3: 0.51 | AK3: 0.54 | AL3: =718150542*AK3/1448 -> 267818.57 | AM3: =+AL3/52 -> 5150.3572 | AN3: =74813*AJ3*0.81 -> 30905.25 | AO3: =+AN3*AP3 -> 9982.3958 | AP3: 0.323 | AQ3: =+AO3/AL3 -> 0.037272978
A4: BOMBONES | B4: CAMARA | C4: =+J4 -> 2 | D4: BOMBON ESCOCES | E4: Criticos | F4: AAA | G4: Crítico - Alta Rotación y Rentabilidad (Control Diario) | H4: Verde | I4: Izquierda_SEGUNDO Rack | J4: 2 | K4: 1 | L4: 1 | M4: 10 | N4: =720*6/1000 -> 4.32 | O4: =+M4*N4 -> 43.2 | P4: =+$AO$18*O4/SUM($O$4:$O$18) -> 358.22459 | Q4: =50.5*17*17/1000000 -> 0.0145945 | R4: =+N4/Q4 -> 296.00192 | S4: =+M4 -> 10 | T4: =+$AO$18*S4/SUM($S$4:$S$18) -> 444.8483 | U4: =+Q4*S4 -> 0.145945 | V4: =105*17/10000 -> 0.1785 | W4: =(66*52.5+126*52.5)*17/1000000 -> 0.17136 | X4: 14.21 | Y4: =+V4/X4 -> 0.012561576 | Z4: =+U4/W4 -> 0.85168651 | AA4: 34.104 | AB4: =+W4/AA4 -> 0.0050246305 | AC4: =+$AN$18*AB4 -> 60.897045 | AD4: =(2.09*2.94*0.75+1.2*1.6*2.09)/AA4*AB4*$AN$18 -> 15.394342 | AE4: =+AC4+AD4 -> 76.291387 | AF4: =+$AP$18*AE4 -> 24.642118 | AG4: =+AE4/O4 -> 1.7660043 | AH4: =+AG4*$AP$18 -> 0.5704194 | AI4: =+O4/$O$1048576 -> 0.010235735
A5: BOMBONES | B5: CAMARA | C5: =+J5 -> 2 | D5: BOMBON SUIZO | E5: Rutina | F5: BBB | G5: Rutina - Baja prioridad (Reposición Automática) | H5: Gris | I5: Izquierda_SEGUNDO Rack | J5: 2 | K5: 1 | L5: 6 | M5: 4 | N5: =680*6/1000 -> 4.08 | O5: =+M5*N5 -> 16.32 | P5: =+$AO$18*O5/SUM($O$4:$O$18) -> 135.32929 | Q5: =38.5*23*16/1000000 -> 0.014168 | R5: =+N5/Q5 -> 287.9729 | S5: =+M5 -> 4 | T5: =+$AO$18*S5/SUM($S$4:$S$18) -> 177.93932 | U5: =+Q5*S5 -> 0.056672 | V5: =100*23/10000 -> 0.23 | W5: =66*50*23/1000000 -> 0.0759 | X5: 14.21 | Y5: =+V5/X5 -> 0.016185785 | Z5: =+U5/W5 -> 0.74666667 | AA5: 34.104 | AB5: =+W5/AA5 -> 0.0022255454 | AC5: =+$AN$18*AB5 -> 26.972956 | AD5: =(2.09*2.94*0.75+1.2*1.6*2.09)/AA5*AB5*$AN$18 -> 6.8185725 | AE5: =+AC5+AD5 -> 33.791528 | AF5: =+$AP$18*AE5 -> 10.914664 | AG5: =+AE5/O5 -> 2.0705593 | AH5: =+AG5*$AP$18 -> 0.66879066 | AI5: =+O5/$O$1048576 -> 0.0038668331
A6: POSTRES | B6: CAMARA | C6: =+J6 -> 2 | D6: POSTRE CASSATA | E6: Rutina | F6: BBB | G6: Rutina - Baja prioridad (Reposición Automática) | H6: Gris | I6: Izquierda_SEGUNDO Rack | J6: 2 | K6: 1 | L6: 5 | M6: 4 | N6: =600*6/1000 -> 3.6 | O6: =+M6*N6 -> 14.4 | P6: =+$AO$18*O6/SUM($O$4:$O$18) -> 119.4082 | Q6: =38.5*23*16/1000000 -> 0.014168 | R6: =+N6/Q6 -> 254.09373 | S6: =+M6 -> 4 | T6: =+$AO$18*S6/SUM($S$4:$S$18) -> 177.93932 | U6: =+Q6*S6 -> 0.056672 | V6: =100*23/10000 -> 0.23 | W6: =66*100*23/1000000/2 -> 0.0759 | X6: 14.21 | Y6: =+V6/X6 -> 0.016185785 | Z6: =+U6/W6 -> 0.74666667 | AA6: 34.104 | AB6: =+W6/AA6 -> 0.0022255454 | AC6: =+$AN$18*AB6 -> 26.972956 | AD6: =(2.09*2.94*0.75+1.2*1.6*2.09)/AA6*AB6*$AN$18 -> 6.8185725 | AE6: =+AC6+AD6 -> 33.791528 | AF6: =+$AP$18*AE6 -> 10.914664 | AG6: =+AE6/O6 -> 2.3466339 | AH6: =+AG6*$AP$18 -> 0.75796275 | AI6: =+O6/$O$1048576 -> 0.0034119116
A7: POSTRES | B7: CAMARA | C7: =+J7 -> 2 | D7: POSTRE ALMENDRADO | E7: Rutina | F7: BBB | G7: Rutina - Baja prioridad (Reposición Automática) | H7: Gris | I7: Izquierda_SEGUNDO Rack | J7: 2 | K7: 1 | L7: 5 | M7: 4 | N7: =672*6/1000 -> 4.032 | O7: =+M7*N7 -> 16.128 | P7: =+$AO$18*O7/SUM($O$4:$O$18) -> 133.73718 | Q7: =38.5*23*16/1000000 -> 0.014168 | R7: =+N7/Q7 -> 284.58498 | S7: =+M7 -> 4 | T7: =+$AO$18*S7/SUM($S$4:$S$18) -> 177.93932 | U7: =+Q7*S7 -> 0.056672 | V7: =100*23/10000 -> 0.23 | W7: =66*100*23/1000000/2 -> 0.0759 | X7: 14.21 | Y7: =+V7/X7 -> 0.016185785 | Z7: =+U7/W7 -> 0.74666667 | AA7: 34.104 | AB7: =+W7/AA7 -> 0.0022255454 | AC7: =+$AN$18*AB7 -> 26.972956 | AD7: =(2.09*2.94*0.75+1.2*1.6*2.09)/AA7*AB7*$AN$18 -> 6.8185725 | AE7: =+AC7+AD7 -> 33.791528 | AF7: =+$AP$18*AE7 -> 10.914664 | AG7: =+AE7/O7 -> 2.0952088 | AH7: =+AG7*$AP$18 -> 0.67675246 | AI7: =+O7/$O$1048576 -> 0.0038213409
A8: BOMBONES | B8: CAMARA | C8: =+J8 -> 2 | D8: BOMBON FRUTEZZA | E8: Estrategicos Financieros | F8: ABB | G8: Estratégico - Alto Margen, Bajo Espacio (Maximizar Stock) | H8: Azul | I8: Izquierda_SEGUNDO Rack | J8: 2 | K8: 1 | L8: 3 | M8: 10 | N8: =592*6/1000 -> 3.552 | O8: =+M8*N8 -> 35.52 | P8: =+$AO$18*O8/SUM($O$4:$O$18) -> 294.54022 | Q8: =40.5*23*13/1000000 -> 0.0121095 | R8: =+N8/Q8 -> 293.32342 | S8: =+M8 -> 10 | T8: =+$AO$18*S8/SUM($S$4:$S$18) -> 444.8483 | U8: =+Q8*S8 -> 0.121095 | V8: =100*23/10000 -> 0.23 | W8: =66*100*23/1000000 -> 0.1518 | X8: 14.21 | Y8: =+V8/X8 -> 0.016185785 | Z8: =+U8/W8 -> 0.79772727 | AA8: 34.104 | AB8: =+W8/AA8 -> 0.0044510908 | AC8: =+$AN$18*AB8 -> 53.945912 | AD8: =(2.09*2.94*0.75+1.2*1.6*2.09)/AA8*AB8*$AN$18 -> 13.637145 | AE8: =+AC8+AD8 -> 67.583057 | AF8: =+$AP$18*AE8 -> 21.829327 | AG8: =+AE8/O8 -> 1.9026761 | AH8: =+AG8*$AP$18 -> 0.61456439 | AI8: =+O8/$O$1048576 -> 0.0084160485
A9: POSTRES | B9: CAMARA | C9: =+J9 -> 2 | D9: POSTRE CROCANTINO | E9: Rutina | F9: BBB | G9: Rutina - Baja prioridad (Reposición Automática) | H9: Gris | I9: Izquierda_SEGUNDO Rack | J9: 2 | K9: 1 | L9: 6 | M9: 4 | N9: =680*4/1000 -> 2.72 | O9: =+M9*N9 -> 10.88 | P9: =+$AO$18*O9/SUM($O$4:$O$18) -> 90.219526 | Q9: =33*22.5*12/1000000 -> 0.00891 | R9: =+N9/Q9 -> 305.27497 | S9: =+M9 -> 4 | T9: =+$AO$18*S9/SUM($S$4:$S$18) -> 177.93932 | U9: =+Q9*S9 -> 0.03564 | V9: =50*22.5/10000 -> 0.1125 | W9: =97*50*22.5/1000000/2 -> 0.0545625 | X9: 14.21 | Y9: =+V9/X9 -> 0.0079169599 | Z9: =+U9/W9 -> 0.65319588 | AA9: 34.104 | AB9: =+W9/AA9 -> 0.0015998856 | AC9: =+$AN$18*AB9 -> 19.390144 | AD9: =(2.09*2.94*0.75+1.2*1.6*2.09)/AA9*AB9*$AN$18 -> 4.9016912 | AE9: =+AC9+AD9 -> 24.291835 | AF9: =+$AP$18*AE9 -> 7.8462626 | AG9: =+AE9/O9 -> 2.2327054 | AH9: =+AG9*$AP$18 -> 0.72116385 | AI9: =+O9/$O$1048576 -> 0.0025778887
A10: POSTRES | B10: CAMARA | C10: =+J10 -> 2 | D10: POSTRE DELICIA | E10: Rutina | F10: BBB | G10: Rutina - Baja prioridad (Reposición Automática) | H10: Gris | I10: Izquierda_SEGUNDO Rack | J10: 2 | K10: 1 | L10: 6 | M10: 4 | N10: =600*4/1000 -> 2.4 | O10: =+M10*N10 -> 9.6 | P10: =+$AO$18*O10/SUM($O$4:$O$18) -> 79.605464 | Q10: =33*22.5*12/1000000 -> 0.00891 | R10: =+N10/Q10 -> 269.36027 | S10: =+M10 -> 4 | T10: =+$AO$18*S10/SUM($S$4:$S$18) -> 177.93932 | U10: =+Q10*S10 -> 0.03564 | V10: =50*22.5/10000 -> 0.1125 | W10: =97*50*22.5/1000000/2 -> 0.0545625 | X10: 14.21 | Y10: =+V10/X10 -> 0.0079169599 | Z10: =+U10/W10 -> 0.65319588 | AA10: 34.104 | AB10: =+W10/AA10 -> 0.0015998856 | AC10: =+$AN$18*AB10 -> 19.390144 | AD10: =(2.09*2.94*0.75+1.2*1.6*2.09)/AA10*AB10*$AN$18 -> 4.9016912 | AE10: =+AC10+AD10 -> 24.291835 | AF10: =+$AP$18*AE10 -> 7.8462626 | AG10: =+AE10/O10 -> 2.5303995 | AH10: =+AG10*$AP$18 -> 0.81731903 | AI10: =+O10/$O$1048576 -> 0.0022746077
A11: BOMBONES | B11: CAMARA | C11: =+J11 -> 2 | D11: BOMBON CROCANTE | E11: Criticos | F11: AAA | G11: Crítico - Alta Rotación y Rentabilidad (Control Diario) | H11: Verde | I11: Izquierda_SEGUNDO Rack | J11: 2 | K11: 1 | L11: 2 | M11: 11 | N11: =560*6/1000 -> 3.36 | O11: =+M11*N11 -> 36.96 | P11: =+$AO$18*O11/SUM($O$4:$O$18) -> 306.48104 | Q11: =40.5*23*13/1000000 -> 0.0121095 | R11: =+N11/Q11 -> 277.4681 | S11: =+M11 -> 11 | T11: =+$AO$18*S11/SUM($S$4:$S$18) -> 489.33313 | U11: =+Q11*S11 -> 0.1332045 | V11: =100*23/10000 -> 0.23 | W11: =66*100*23/1000000 -> 0.1518 | X11: 14.21 | Y11: =+V11/X11 -> 0.016185785 | Z11: =+U11/W11 -> 0.8775 | AA11: 34.104 | AB11: =+W11/AA11 -> 0.0044510908 | AC11: =+$AN$18*AB11 -> 53.945912 | AD11: =(2.09*2.94*0.75+1.2*1.6*2.09)/AA11*AB11*$AN$18 -> 13.637145 | AE11: =+AC11+AD11 -> 67.583057 | AF11: =+$AP$18*AE11 -> 21.829327 | AG11: =+AE11/O11 -> 1.8285459 | AH11: =+AG11*$AP$18 -> 0.59062033 | AI11: =+O11/$O$1048576 -> 0.0087572396
A12: BOMBONES | B12: CAMARA | C12: =+J12 -> 2 | D12: BOMBON SECRETO | E12: Estrategicos Financieros | F12: ABB | G12: Estratégico - Alto Margen, Bajo Espacio (Maximizar Stock) | H12: Azul | I12: Izquierda_SEGUNDO Rack | J12: 2 | K12: 1 | L12: 4 | M12: 10 | N12: =498*6/1000 -> 2.988 | O12: =+M12*N12 -> 29.88 | P12: =+$AO$18*O12/SUM($O$4:$O$18) -> 247.77201 | Q12: =42.5*19*13.5/1000000 -> 0.01090125 | R12: =+N12/Q12 -> 274.09701 | S12: =+M12 -> 10 | T12: =+$AO$18*S12/SUM($S$4:$S$18) -> 444.8483 | U12: =+Q12*S12 -> 0.1090125 | V12: =100*19/10000 -> 0.19 | W12: =66*100*19/1000000 -> 0.1254 | X12: 14.21 | Y12: =+V12/X12 -> 0.013370866 | Z12: =+U12/W12 -> 0.86931818 | AA12: 34.104 | AB12: =+W12/AA12 -> 0.003676988 | AC12: =+$AN$18*AB12 -> 44.564014 | AD12: =(2.09*2.94*0.75+1.2*1.6*2.09)/AA12*AB12*$AN$18 -> 11.265468 | AE12: =+AC12+AD12 -> 55.829482 | AF12: =+$AP$18*AE12 -> 18.032923 | AG12: =+AE12/O12 -> 1.8684565 | AH12: =+AG12*$AP$18 -> 0.60351146 | AI12: =+O12/$O$1048576 -> 0.0070797165
A13: FAMILIARES | B13: CAMARA | C13: =+J13 -> 2 | D13: FAMILIARES_1 | E13: Criticos | F13: AAA | G13: Crítico - Alta Rotación y Rentabilidad (Control Diario) | H13: Verde | I13: Izquierda_SEGUNDO Rack | J13: 2 | K13: 2 | L13: 1 | M13: 4.5 | N13: =1.6*6 -> 9.6 | O13: =+N13*M13 -> 43.2 | P13: =+$AO$18*O13/SUM($O$4:$O$18) -> 358.22459 | Q13: =39*20*30/1000000 -> 0.0234 | R13: =+N13/Q13 -> 410.25641 | S13: =+M13 -> 4.5 | T13: =+$AO$18*S13/SUM($S$4:$S$18) -> 200.18173 | U13: =+Q13*S13 -> 0.1053 | V13: =1*1.34/6 -> 0.22333333 | W13: =1.34/6*0.7 -> 0.15633333 | X13: 14.21 | Y13: =+V13/X13 -> 0.015716631 | Z13: =+U13/W13 -> 0.67356077 | AA13: 34.104 | AB13: =+W13/AA13 -> 0.0045840175 | AC13: =+$AN$18*AB13 -> 55.556945 | AD13: =(2.09*2.94*0.75+1.2*1.6*2.09)/AA13*AB13*$AN$18 -> 14.044403 | AE13: =+AC13+AD13 -> 69.601347 | AF13: =+$AP$18*AE13 -> 22.481235 | AG13: =+AE13/O13 -> 1.6111423 | AH13: =+AG13*$AP$18 -> 0.52039896 | AI13: =+O13/$O$1048576 -> 0.010235735
A14: FAMILIARES | B14: CAMARA | C14: =+J14 -> 2 | D14: FAMILIARES_2 | E14: Criticos | F14: AAA | G14: Crítico - Alta Rotación y Rentabilidad (Control Diario) | H14: Verde | I14: Izquierda_SEGUNDO Rack | J14: 2 | K14: 2 | L14: 2 | M14: 4.5 | N14: =1.6*6 -> 9.6 | O14: =+N14*M14 -> 43.2 | P14: =+$AO$18*O14/SUM($O$4:$O$18) -> 358.22459 | Q14: =39*20*30/1000000 -> 0.0234 | R14: =+N14/Q14 -> 410.25641 | S14: =+M14 -> 4.5 | T14: =+$AO$18*S14/SUM($S$4:$S$18) -> 200.18173 | U14: =+Q14*S14 -> 0.1053 | V14: =1*1.34/6 -> 0.22333333 | W14: =1.34/6*0.7 -> 0.15633333 | X14: 14.21 | Y14: =+V14/X14 -> 0.015716631 | Z14: =+U14/W14 -> 0.67356077 | AA14: 34.104 | AB14: =+W14/AA14 -> 0.0045840175 | AC14: =+$AN$18*AB14 -> 55.556945 | AD14: =(2.09*2.94*0.75+1.2*1.6*2.09)/AA14*AB14*$AN$18 -> 14.044403 | AE14: =+AC14+AD14 -> 69.601347 | AF14: =+$AP$18*AE14 -> 22.481235 | AG14: =+AE14/O14 -> 1.6111423 | AH14: =+AG14*$AP$18 -> 0.52039896 | AI14: =+O14/$O$1048576 -> 0.010235735
A15: FAMILIARES | B15: CAMARA | C15: =+J15 -> 2 | D15: FAMILIARES_2 | E15: Criticos | F15: AAA | G15: Crítico - Alta Rotación y Rentabilidad (Control Diario) | H15: Verde | I15: Izquierda_SEGUNDO Rack | J15: 2 | K15: 2 | L15: 3 | M15: 4.5 | N15: =1.6*6 -> 9.6 | O15: =+N15*M15 -> 43.2 | P15: =+$AO$18*O15/SUM($O$4:$O$18) -> 358.22459 | Q15: =39*20*30/1000000 -> 0.0234 | R15: =+N15/Q15 -> 410.25641 | S15: =+M15 -> 4.5 | T15: =+$AO$18*S15/SUM($S$4:$S$18) -> 200.18173 | U15: =+Q15*S15 -> 0.1053 | V15: =1*1.34/6 -> 0.22333333 | W15: =1.34/6*0.7 -> 0.15633333 | X15: 14.21 | Y15: =+V15/X15 -> 0.015716631 | Z15: =+U15/W15 -> 0.67356077 | AA15: 34.104 | AB15: =+W15/AA15 -> 0.0045840175 | AC15: =+$AN$18*AB15 -> 55.556945 | AD15: =(2.09*2.94*0.75+1.2*1.6*2.09)/AA15*AB15*$AN$18 -> 14.044403 | AE15: =+AC15+AD15 -> 69.601347 | AF15: =+$AP$18*AE15 -> 22.481235 | AG15: =+AE15/O15 -> 1.6111423 | AH15: =+AG15*$AP$18 -> 0.52039896 | AI15: =+O15/$O$1048576 -> 0.010235735
A16: FAMILIARES | B16: CAMARA | C16: =+J16 -> 2 | D16: FAMILIARES_3 | E16: Criticos | F16: AAA | G16: Crítico - Alta Rotación y Rentabilidad (Control Diario) | H16: Verde | I16: Izquierda_SEGUNDO Rack | J16: 2 | K16: 2 | L16: 4 | M16: 4.5 | N16: =1.6*6 -> 9.6 | O16: =+N16*M16 -> 43.2 | P16: =+$AO$18*O16/SUM($O$4:$O$18) -> 358.22459 | Q16: =39*20*30/1000000 -> 0.0234 | R16: =+N16/Q16 -> 410.25641 | S16: =+M16 -> 4.5 | T16: =+$AO$18*S16/SUM($S$4:$S$18) -> 200.18173 | U16: =+Q16*S16 -> 0.1053 | V16: =1*1.34/6 -> 0.22333333 | W16: =1.34/6*0.7 -> 0.15633333 | X16: 14.21 | Y16: =+V16/X16 -> 0.015716631 | Z16: =+U16/W16 -> 0.67356077 | AA16: 34.104 | AB16: =+W16/AA16 -> 0.0045840175 | AC16: =+$AN$18*AB16 -> 55.556945 | AD16: =(2.09*2.94*0.75+1.2*1.6*2.09)/AA16*AB16*$AN$18 -> 14.044403 | AE16: =+AC16+AD16 -> 69.601347 | AF16: =+$AP$18*AE16 -> 22.481235 | AG16: =+AE16/O16 -> 1.6111423 | AH16: =+AG16*$AP$18 -> 0.52039896 | AI16: =+O16/$O$1048576 -> 0.010235735
A17: FAMILIARES | B17: CAMARA | C17: =+J17 -> 2 | D17: FAMILIARES_3 | E17: Criticos | F17: AAA | G17: Crítico - Alta Rotación y Rentabilidad (Control Diario) | H17: Verde | I17: Izquierda_SEGUNDO Rack | J17: 2 | K17: 2 | L17: 5 | M17: 4.5 | N17: =1.6*6 -> 9.6 | O17: =+N17*M17 -> 43.2 | P17: =+$AO$18*O17/SUM($O$4:$O$18) -> 358.22459 | Q17: =39*20*30/1000000 -> 0.0234 | R17: =+N17/Q17 -> 410.25641 | S17: =+M17 -> 4.5 | T17: =+$AO$18*S17/SUM($S$4:$S$18) -> 200.18173 | U17: =+Q17*S17 -> 0.1053 | V17: =1*1.34/6 -> 0.22333333 | W17: =1.34/6*0.7 -> 0.15633333 | X17: 14.21 | Y17: =+V17/X17 -> 0.015716631 | Z17: =+U17/W17 -> 0.67356077 | AA17: 34.104 | AB17: =+W17/AA17 -> 0.0045840175 | AC17: =+$AN$18*AB17 -> 55.556945 | AD17: =(2.09*2.94*0.75+1.2*1.6*2.09)/AA17*AB17*$AN$18 -> 14.044403 | AE17: =+AC17+AD17 -> 69.601347 | AF17: =+$AP$18*AE17 -> 22.481235 | AG17: =+AE17/O17 -> 1.6111423 | AH17: =+AG17*$AP$18 -> 0.52039896 | AI17: =+O17/$O$1048576 -> 0.010235735
A18: FAMILIARES | B18: CAMARA | C18: =+J18 -> 2 | D18: FAMILIARES_4 | E18: Criticos | F18: AAA | G18: Crítico - Alta Rotación y Rentabilidad (Control Diario) | H18: Verde | I18: Izquierda_SEGUNDO Rack | J18: 2 | K18: 2 | L18: 6 | M18: 4.5 | N18: =1.6*6 -> 9.6 | O18: =+N18*M18 -> 43.2 | P18: =+$AO$18*O18/SUM($O$4:$O$18) -> 358.22459 | Q18: =39*20*30/1000000 -> 0.0234 | R18: =+N18/Q18 -> 410.25641 | S18: =+M18 -> 4.5 | T18: =+$AO$18*S18/SUM($S$4:$S$18) -> 200.18173 | U18: =+Q18*S18 -> 0.1053 | V18: =1*1.34/6 -> 0.22333333 | W18: =1.34/6*0.7 -> 0.15633333 | X18: 14.21 | Y18: =+V18/X18 -> 0.015716631 | Z18: =+U18/W18 -> 0.67356077 | AA18: 34.104 | AB18: =+W18/AA18 -> 0.0045840175 | AC18: =+$AN$18*AB18 -> 55.556945 | AD18: =(2.09*2.94*0.75+1.2*1.6*2.09)/AA18*AB18*$AN$18 -> 14.044403 | AE18: =+AC18+AD18 -> 69.601347 | AF18: =+$AP$18*AE18 -> 22.481235 | AG18: =+AE18/O18 -> 1.6111423 | AH18: =+AG18*$AP$18 -> 0.52039896 | AI18: =+O18/$O$1048576 -> 0.010235735 | AJ18: 0.2 | AK18: 0.177 | AL18: =718150542*AK18/1448 -> 87784.976 | AM18: =+AL18/52 -> 1688.1726 | AN18: =74813*AJ18*0.81 -> 12119.706 | AO18: =+AP18*AN18 -> 3914.665 | AP18: 0.323 | AQ18: =+AO18/AL18 -> 0.044593793
A19: TENTACIONES | B19: CAMARA | C19: =+J19 -> 3 | D19: TENTACIONES_1 (Dulce de Leche Granizado/Chocolate con Almendras/Limon/Granizado/Cookie) | E19: Criticos | F19: AAA | G19: Crítico - Alta Rotación y Rentabilidad (Control Diario) | H19: Verde | I19: Izquierda_TERCER Rack | J19: 3 | K19: 1 | L19: 6 | M19: 54 | N19: 4.14 | O19: =+N19*M19 -> 223.56 | P19: =+$AO$20*O19/SUM($O$19:$O$20) -> 735.67741 | Q19: =23.5*32.5*14/1000000 -> 0.0106925 | R19: =+N19/Q19 -> 387.18728 | S19: 54 | T19: =+$AO$20*S19/SUM($S$19:$S$20) -> 735.67741 | U19: =+Q19*S19 -> 0.577395 | V19: =+(68+65.5)*100/10000 -> 1.335 | W19: =(51+70)*(68+65.5)*100/1000000 -> 1.61535 | X19: 14.21 | Y19: =+V19/X19 -> 0.093947924 | Z19: =+U19/W19 -> 0.35744266 | AA19: 34.104 | AB19: =+W19/AA19 -> 0.047365412 | AC19: =+$AN$20*AB19 -> 251.72306 | AD19: =(2.09*2.94*0.75+1.2*1.6*2.09)/AA19*AB19*$AN$20 -> 63.633809 | AE19: =+AC19+AD19 -> 315.35687 | AF19: =+$AP$20*AE19 -> 101.86027 | AG19: =+AE19/O19 -> 1.410614 | AH19: =+AG19*$AP$20 -> 0.45562832 | AI19: =+O19/$O$1048576 -> 0.052969927
A20: TENTACIONES | B20: CAMARA | C20: =+J20 -> 3 | D20: TENTACIONES_2 (Toddy galletitas/Frutilla/Crema Americana/Chocolate/Menta Granizada/Vainilla/Cadbury y Cocolate con Almendras) | E20: Rutina | F20: BBC | G20: Rutina - Baja prioridad (Reposición Automática) | H20: Gris | I20: Izquierda_TERCER Rack | J20: 3 | K20: 2 | L20: 6 | M20: 72 | N20: 4.14 | O20: =+N20*M20 -> 298.08 | P20: =+$AO$20*O20/SUM($O$19:$O$20) -> 980.90321 | Q20: =23.5*32.5*14/1000000 -> 0.0106925 | R20: =+N20/Q20 -> 387.18728 | S20: 72 | T20: =+$AO$20*S20/SUM($S$19:$S$20) -> 980.90321 | U20: =+Q20*S20 -> 0.76986 | V20: =+(68+65.5)*100/10000 -> 1.335 | W20: =(51+70)*(68+65.5)*100/1000000 -> 1.61535 | X20: 14.21 | Y20: =+V20/X20 -> 0.093947924 | Z20: =+U20/W20 -> 0.47659021 | AA20: 34.104 | AB20: =+W20/AA20 -> 0.047365412 | AC20: =+$AN$20*AB20 -> 251.72306 | AD20: =(2.09*2.94*0.75+1.2*1.6*2.09)/AA20*AB20*$AN$20 -> 63.633809 | AE20: =+AC20+AD20 -> 315.35687 | AF20: =+$AP$20*AE20 -> 101.86027 | AG20: =+AE20/O20 -> 1.0579605 | AH20: =+AG20*$AP$20 -> 0.34172124 | AI20: =+O20/$O$1048576 -> 0.070626569 | AJ20: 0.0877 | AK20: 0.0519 | AL20: =718150542*AK20/1448 -> 25740.341 | AM20: =+AL20/52 -> 495.00655 | AN20: =74813*AJ20*0.81 -> 5314.4911 | AO20: =+AP20*AN20 -> 1716.5806 | AP20: 0.323 | AQ20: =+AO20/AL20 -> 0.066688341
A21: PALITOS | B21: CAMARA | C21: =+J21 -> 4 | D21: PALITOS_AGUA | E21: Rutina | F21: BBB | G21: Rutina - Baja prioridad (Reposición Automática) | H21: Gris | I21: Derecha_CUARTO Rack | J21: 4 | K21: 2-3 | L21: Nivel 2: P[1,2,3] - Nivel 3: P[1] | M21: 60 | N21: 5.5 | O21: =+N21*M21 -> 330 | P21: =+$AO$26*O21/SUM($O$21:$O$26) -> 536.42284 | Q21: =+(39*25*26)/1000000 -> 0.02535 | R21: =+N21/Q21 -> 216.96252 | S21: 60 | T21: =+$AO$26*S21/SUM($S$21:$S$26) -> 559.52239 | U21: =+Q21*S21 -> 1.521 | V21: =+(2.95*1.02+0.75*1.02) -> 3.774 | W21: 2.6418 | X21: 14.21 | Y21: =+V21/X21 -> 0.26558761 | Z21: =+U21/W21 -> 0.57574381 | AA21: 34.104 | AB21: =+W21/AA21 -> 0.077463054 | AC21: =+$AN$26*AB21 -> 382.43217 | AD21: =(2.09*2.94*0.75+1.2*1.6*2.09)/AA21*AB21*$AN$26 -> 96.676149 | AE21: =+AC21+AD21 -> 479.10832 | AF21: =+$AP$26*AE21 -> 154.75199 | AG21: =+AE21/O21 -> 1.4518434 | AH21: =+AG21*$AP$26 -> 0.46894542 | AI21: =+O21/$O$1048576 -> 0.07818964
A22: PALITOS | B22: CAMARA | C22: =+J22 -> 4 | D22: PALITOS_CREMOSO | E22: Rutina | F22: BBB | G22: Rutina - Baja prioridad (Reposición Automática) | H22: Gris | I22: Derecha_CUARTO Rack | J22: 4 | K22: 2 | L22: 3 | M22: 12 | N22: 4 | O22: =+N22*M22 -> 48 | P22: =+$AO$26*O22/SUM($O$21:$O$26) -> 78.02514 | Q22: =+(39*25*26)/1000000 -> 0.02535 | R22: =+N22/Q22 -> 157.79093 | S22: 12 | T22: =+$AO$26*S22/SUM($S$21:$S$26) -> 111.90448 | U22: =+Q22*S22 -> 0.3042 | V22: =+(0.75*1.02) -> 0.765 | W22: 0.5355 | X22: 14.21 | Y22: =+V22/X22 -> 0.053835327 | Z22: =+U22/W22 -> 0.56806723 | AA22: 34.104 | AB22: =+W22/AA22 -> 0.01570197 | AC22: =+$AN$26*AB22 -> 77.520035 | AD22: =(2.09*2.94*0.75+1.2*1.6*2.09)/AA22*AB22*$AN$26 -> 19.596517 | AE22: =+AC22+AD22 -> 97.116552 | AF22: =+$AP$26*AE22 -> 31.368646 | AG22: =+AE22/O22 -> 2.0232615 | AH22: =+AG22*$AP$26 -> 0.65351346 | AI22: =+O22/$O$1048576 -> 0.011373039
A23: PALITOS | B23: CAMARA | C23: =+J23 -> 4 | D23: PALITOS_BOMBON | E23: Criticos | F23: AAA | G23: Crítico - Alta Rotación y Rentabilidad (Control Diario) | H23: Verde | I23: Derecha_CUARTO Rack | J23: 4 | K23: 1 | L23: P[1-2-3] | M23: 37 | N23: 5.1 | O23: =+N23*M23 -> 188.7 | P23: =+$AO$26*O23/SUM($O$21:$O$26) -> 306.73633 | Q23: =+(39*25*26)/1000000 -> 0.02535 | R23: =+N23/Q23 -> 201.18343 | S23: 37 | T23: =+$AO$26*S23/SUM($S$21:$S$26) -> 345.03881 | U23: =+Q23*S23 -> 0.93795 | V23: =+(2.95*1.02) -> 3.009 | W23: 1.56468 | X23: 14.21 | Y23: =+V23/X23 -> 0.21175229 | Z23: =+U23/W23 -> 0.59945165 | AA23: 34.104 | AB23: =+W23/AA23 -> 0.045879662 | AC23: =+$AN$26*AB23 -> 226.50616 | AD23: =(2.09*2.94*0.75+1.2*1.6*2.09)/AA23*AB23*$AN$26 -> 57.259155 | AE23: =+AC23+AD23 -> 283.76532 | AF23: =+$AP$26*AE23 -> 91.656197 | AG23: =+AE23/O23 -> 1.5037908 | AH23: =+AG23*$AP$26 -> 0.48572441 | AI23: =+O23/$O$1048576 -> 0.044710258
A24: TORTAS | B24: CAMARA | C24: =+J24 -> 4 | D24: TORTAS | E24: Criticos | F24: AAA | G24: Crítico - Alta Rotación y Rentabilidad (Control Diario) | H24: Verde | I24: Derecha_CUARTO Rack | J24: 4 | K24: 3 | L24: 4 | M24: 18 | N24: 6.27 | O24: =+N24*M24 -> 112.86 | P24: =+$AO$26*O24/SUM($O$21:$O$26) -> 183.45661 | Q24: =+(45*23*21.5)/1000000 -> 0.0222525 | R24: =+N24/Q24 -> 281.76609 | S24: 18 | T24: =+$AO$26*S24/SUM($S$21:$S$26) -> 167.85672 | U24: =+Q24*S24 -> 0.400545 | V24: =+(0.75*1.02) -> 0.765 | W24: 0.5355 | X24: 14.21 | Y24: =+V24/X24 -> 0.053835327 | Z24: =+U24/W24 -> 0.74798319 | AA24: 34.104 | AB24: =+W24/AA24 -> 0.01570197 | AC24: =+$AN$26*AB24 -> 77.520035 | AD24: =(2.09*2.94*0.75+1.2*1.6*2.09)/AA24*AB24*$AN$26 -> 19.596517 | AE24: =+AC24+AD24 -> 97.116552 | AF24: =+$AP$26*AE24 -> 31.368646 | AG24: =+AE24/O24 -> 0.86050462 | AH24: =+AG24*$AP$26 -> 0.27794299 | AI24: =+O24/$O$1048576 -> 0.026740857
A25: BOCADITOS | B25: CAMARA | C25: =+J25 -> 4 | D25: BOCADITOS | E25: Estrategicos Financieros | F25: ABB | G25: Estratégico - Alto Margen, Bajo Espacio (Maximizar Stock) | H25: Azul | I25: Derecha_CUARTO Rack | J25: 4 | K25: 1 | L25: 4 | M25: 18 | N25: 2.88 | O25: =+N25*M25 -> 51.84 | P25: =+$AO$26*O25/SUM($O$21:$O$26) -> 84.267151 | Q25: =+(31.5*21.5*24.5)/1000000 -> 0.016592625 | R25: =+N25/Q25 -> 173.57109 | S25: 18 | T25: =+$AO$26*S25/SUM($S$21:$S$26) -> 167.85672 | U25: =+Q25*S25 -> 0.29866725 | V25: =+(0.75*1.02) -> 0.765 | W25: 0.3978 | X25: 14.21 | Y25: =+V25/X25 -> 0.053835327 | Z25: =+U25/W25 -> 0.75079751 | AA25: 34.104 | AB25: =+W25/AA25 -> 0.011664321 | AC25: =+$AN$26*AB25 -> 57.586312 | AD25: =(2.09*2.94*0.75+1.2*1.6*2.09)/AA25*AB25*$AN$26 -> 14.557412 | AE25: =+AC25+AD25 -> 72.143724 | AF25: =+$AP$26*AE25 -> 23.302423 | AG25: =+AE25/O25 -> 1.3916613 | AH25: =+AG25*$AP$26 -> 0.44950661 | AI25: =+O25/$O$1048576 -> 0.012282882
A26: FAMILIARES | B26: CAMARA | C26: =+J26 -> 4 | D26: FAMILIARES_2 | E26: Criticos | F26: AAA | G26: Crítico - Alta Rotación y Rentabilidad (Control Diario) | H26: Verde | I26: Derecha_CUARTO Rack | J26: 4 | K26: 3 | L26: P[2-3] | M26: 26 | N26: 9.6 | O26: =+N26*M26 -> 249.6 | P26: =+$AO$26*O26/SUM($O$21:$O$26) -> 405.73073 | Q26: =39*20*30/1000000 -> 0.0234 | R26: =+N26/Q26 -> 410.25641 | S26: 26 | T26: =+$AO$26*S26/SUM($S$21:$S$26) -> 242.4597 | U26: =+Q26*S26 -> 0.6084 | V26: =1.34*1.02 -> 1.3668 | W26: 0.95676 | X26: 14.21 | Y26: =+V26/X26 -> 0.096185785 | Z26: =+U26/W26 -> 0.63589615 | AA26: 34.104 | AB26: =+W26/AA26 -> 0.028054187 | AC26: =+$AN$26*AB26 -> 138.50246 | AD26: =(2.09*2.94*0.75+1.2*1.6*2.09)/AA26*AB26*$AN$26 -> 35.012443 | AE26: =+AC26+AD26 -> 173.51491 | AF26: =+$AP$26*AE26 -> 56.045315 | AG26: =+AE26/O26 -> 0.6951719 | AH26: =+AG26*$AP$26 -> 0.22454052 | AI26: =+O26/$O$1048576 -> 0.0591398 | AJ26: =0.074+0.00747 -> 0.08147 | AK26: =0.0655+0.0237 -> 0.0892 | AL26: =718150542*AK26/1448 -> 44239.66 | AM26: =+AL26/52 -> 850.7627 | AN26: =74813*AJ26*0.81 -> 4936.9622 | AO26: =+AP26*AN26 -> 1594.6388 | AP26: 0.323 | AQ26: =+AO26/AL26 -> 0.036045458
A27: FRIZZIO | B27: CAMARA | C27: =+J27 -> 3 | D27: FRIZZIO PIZZA JAMON Y QUESO | E27: Rutina | F27: BBB | G27: Rutina - Baja prioridad (Reposición Automática) | H27: Gris | I27: Izquierda_TERCER Rack | J27: 3 | K27: 3 | L27: 2 | M27: 4 | N27: =535*11/1000 -> 5.885 | O27: =+N27*M27 -> 23.54 | P27: =+$AO$36*O27/SUM($O$27:$O$36) -> 109.08543 | Q27: =30*32*28.5/1000000 -> 0.02736 | R27: =+N27/Q27 -> 215.09503 | S27: 4 | T27: =+$AO$36*S27/SUM($S$27:$S$36) -> 100.07926 | U27: =+Q27*S27 -> 0.10944 | V27: =30*32/10000 -> 0.096 | W27: =1.37*1.02*0.7/6 -> 0.16303 | X27: 14.21 | Y27: =+V27/X27 -> 0.0067558058 | Z27: =+U27/W27 -> 0.67128749 | AA27: 34.104 | AB27: =+W27/AA27 -> 0.0047803777 | AC27: =+$AN$26*AB27 -> 23.600544 | AD27: =(2.09*2.94*0.75+1.2*1.6*2.09)/AA27*AB27*$AN$26 -> 5.9660506 | AE27: =+AC27+AD27 -> 29.566595 | AF27: =+$AP$26*AE27 -> 9.5500101 | AG27: =+AE27/O27 -> 1.2560151 | AH27: =+AG27*$AP$26 -> 0.40569287 | AI27: =+O27/$O$1048576 -> 0.0055775276
A28: FRIZZIO | B28: CAMARA | C28: 3 | D28: FRIZZIO PIZZA MUZZA | E28: Rutina | F28: BBB | G28: Rutina - Baja prioridad (Reposición Automática) | H28: Gris | I28: Izquierda_TERCER Rack | J28: 3 | K28: 3 | L28: 3 | M28: 4 | N28: =12*510/1000 -> 6.12 | O28: =+N28*M28 -> 24.48 | P28: =+$AO$36*O28/SUM($O$27:$O$36) -> 113.44143 | Q28: =30*32*28.5/1000000 -> 0.02736 | R28: =+N28/Q28 -> 223.68421 | S28: 4 | T28: =+$AO$36*S28/SUM($S$27:$S$36) -> 100.07926 | U28: =+Q28*S28 -> 0.10944 | V28: =30*32/10000 -> 0.096 | W28: =1.37*1.02*0.7/6 -> 0.16303 | X28: 14.21 | Y28: =+V28/X28 -> 0.0067558058 | Z28: =+U28/W28 -> 0.67128749 | AA28: 34.104 | AB28: =+W28/AA28 -> 0.0047803777 | AC28: =+$AN$26*AB28 -> 23.600544 | AD28: =(2.09*2.94*0.75+1.2*1.6*2.09)/AA28*AB28*$AN$26 -> 5.9660506 | AE28: =+AC28+AD28 -> 29.566595 | AF28: =+$AP$26*AE28 -> 9.5500101 | AG28: =+AE28/O28 -> 1.2077857 | AH28: =+AG28*$AP$26 -> 0.39011479 | AI28: =+O28/$O$1048576 -> 0.0058002496
A29: FRIZZIO | B29: CAMARA | C29: 3 | D29: FRIZZIO PIZZA CASERA | E29: Rutina | F29: BBB | G29: Rutina - Baja prioridad (Reposición Automática) | H29: Gris | I29: Izquierda_TERCER Rack | J29: 3 | K29: 3 | L29: 5 | M29: 2 | N29: =8*665/1000 -> 5.32 | O29: =+N29*M29 -> 10.64 | P29: =+$AO$36*O29/SUM($O$27:$O$36) -> 49.306243 | Q29: =30*32*28.5/1000000 -> 0.02736 | R29: =+N29/Q29 -> 194.44444 | S29: 2 | T29: =+$AO$36*S29/SUM($S$27:$S$36) -> 50.039631 | U29: =+Q29*S29 -> 0.05472 | V29: =30*32/10000 -> 0.096 | W29: =1.37*1.02*0.7/6 -> 0.16303 | X29: 14.21 | Y29: =+V29/X29 -> 0.0067558058 | Z29: =+U29/W29 -> 0.33564375 | AA29: 34.104 | AB29: =+W29/AA29 -> 0.0047803777 | AC29: =+$AN$26*AB29 -> 23.600544 | AD29: =(2.09*2.94*0.75+1.2*1.6*2.09)/AA29*AB29*$AN$26 -> 5.9660506 | AE29: =+AC29+AD29 -> 29.566595 | AF29: =+$AP$26*AE29 -> 9.5500101 | AG29: =+AE29/O29 -> 2.7788153 | AH29: =+AG29*$AP$26 -> 0.89755734 | AI29: =+O29/$O$1048576 -> 0.0025210235
A30: FRIZZIO | B30: CAMARA | C30: 3 | D30: FRIZZIO PIZZA CEBOLLA | E30: Rutina | F30: BBB | G30: Rutina - Baja prioridad (Reposición Automática) | H30: Gris | I30: Izquierda_TERCER Rack | J30: 3 | K30: 3 | L30: 5 | M30: 2 | N30: =11*540/1000 -> 5.94 | O30: =+N30*M30 -> 11.88 | P30: =+$AO$36*O30/SUM($O$27:$O$36) -> 55.05246 | Q30: =30*32*28.5/1000000 -> 0.02736 | R30: =+N30/Q30 -> 217.10526 | S30: 2 | T30: =+$AO$36*S30/SUM($S$27:$S$36) -> 50.039631 | U30: =+Q30*S30 -> 0.05472 | V30: =30*32/10000 -> 0.096 | W30: =1.37*1.02*0.7/6 -> 0.16303 | X30: 14.21 | Y30: =+V30/X30 -> 0.0067558058 | Z30: =+U30/W30 -> 0.33564375 | AA30: 34.104 | AB30: =+W30/AA30 -> 0.0047803777 | AC30: =+$AN$26*AB30 -> 23.600544 | AD30: =(2.09*2.94*0.75+1.2*1.6*2.09)/AA30*AB30*$AN$26 -> 5.9660506 | AE30: =+AC30+AD30 -> 29.566595 | AF30: =+$AP$26*AE30 -> 9.5500101 | AG30: =+AE30/O30 -> 2.4887706 | AH30: =+AG30*$AP$26 -> 0.8038729 | AI30: =+O30/$O$1048576 -> 0.002814827
A31: FRIZZIO | B31: CAMARA | C31: 3 | D31: FRIZZIO PIZZA INTEGRAL | E31: Rutina | F31: BBB | G31: Rutina - Baja prioridad (Reposición Automática) | H31: Gris | I31: Izquierda_TERCER Rack | J31: 3 | K31: 3 | L31: 6 | M31: 2 | N31: =12*530/1000 -> 6.36 | O31: =+N31*M31 -> 12.72 | P31: =+$AO$36*O31/SUM($O$27:$O$36) -> 58.945058 | Q31: =30*32*28.5/1000000 -> 0.02736 | R31: =+N31/Q31 -> 232.45614 | S31: 2 | T31: =+$AO$36*S31/SUM($S$27:$S$36) -> 50.039631 | U31: =+Q31*S31 -> 0.05472 | V31: =30*32/10000 -> 0.096 | W31: =1.37*1.02*0.7/6 -> 0.16303 | X31: 14.21 | Y31: =+V31/X31 -> 0.0067558058 | Z31: =+U31/W31 -> 0.33564375 | AA31: 34.104 | AB31: =+W31/AA31 -> 0.0047803777 | AC31: =+$AN$26*AB31 -> 23.600544 | AD31: =(2.09*2.94*0.75+1.2*1.6*2.09)/AA31*AB31*$AN$26 -> 5.9660506 | AE31: =+AC31+AD31 -> 29.566595 | AF31: =+$AP$26*AE31 -> 9.5500101 | AG31: =+AE31/O31 -> 2.3244178 | AH31: =+AG31*$AP$26 -> 0.75078696 | AI31: =+O31/$O$1048576 -> 0.0030138552
A32: FRIZZIO | B32: CAMARA | C32: 3 | D32: FRIZZIO MINI PIZZA | E32: Rutina | F32: BBB | G32: Rutina - Baja prioridad (Reposición Automática) | H32: Gris | I32: Izquierda_TERCER Rack | J32: 3 | K32: 3 | L32: 4 | M32: 1 | N32: =20*180/1000 -> 3.6 | O32: =+N32*M32 -> 3.6 | P32: =+$AO$36*O32/SUM($O$27:$O$36) -> 16.682564 | Q32: =25*39.5*23/1000000 -> 0.0227125 | R32: =+N32/Q32 -> 158.50303 | S32: 1 | T32: =+$AO$36*S32/SUM($S$27:$S$36) -> 25.019816 | U32: =+Q32*S32 -> 0.0227125 | V32: =25*39.5/10000 -> 0.09875 | W32: =1.37*1.02*0.7/6 -> 0.16303 | X32: 14.21 | Y32: =+V32/X32 -> 0.0069493315 | Z32: =+U32/W32 -> 0.13931485 | AA32: 34.104 | AB32: =+W32/AA32 -> 0.0047803777 | AC32: =+$AN$26*AB32 -> 23.600544 | AD32: =(2.09*2.94*0.75+1.2*1.6*2.09)/AA32*AB32*$AN$26 -> 5.9660506 | AE32: =+AC32+AD32 -> 29.566595 | AF32: =+$AP$26*AE32 -> 9.5500101 | AG32: =+AE32/O32 -> 8.212943 | AH32: =+AG32*$AP$26 -> 2.6527806 | AI32: =+O32/$O$1048576 -> 0.00085297789
A33: FRIZZIO | B33: CAMARA | C33: 3 | D33: PECHUGUITAS | E33: Rutina | F33: CCC | G33: Rutina - Baja prioridad (Reposición Automática) | H33: Gris | I33: Izquierda_TERCER Rack | J33: 3 | K33: 3 | L33: 4 | M33: 2 | N33: =16*380/1000 -> 6.08 | O33: =+N33*M33 -> 12.16 | P33: =+$AO$36*O33/SUM($O$27:$O$36) -> 56.349992 | Q33: =25*39.5*23/1000000 -> 0.0227125 | R33: =+N33/Q33 -> 267.694 | S33: 2 | T33: =+$AO$36*S33/SUM($S$27:$S$36) -> 50.039631 | U33: =+Q33*S33 -> 0.045425 | V33: =25*39.5/10000 -> 0.09875 | W33: =1.37*1.02*0.7/6 -> 0.16303 | X33: 14.21 | Y33: =+V33/X33 -> 0.0069493315 | Z33: =+U33/W33 -> 0.2786297 | AA33: 34.104 | AB33: =+W33/AA33 -> 0.0047803777 | AC33: =+$AN$26*AB33 -> 23.600544 | AD33: =(2.09*2.94*0.75+1.2*1.6*2.09)/AA33*AB33*$AN$26 -> 5.9660506 | AE33: =+AC33+AD33 -> 29.566595 | AF33: =+$AP$26*AE33 -> 9.5500101 | AG33: =+AE33/O33 -> 2.4314634 | AH33: =+AG33*$AP$26 -> 0.78536267 | AI33: =+O33/$O$1048576 -> 0.0028811698
A34: FRIZZIO | B34: CAMARA | C34: 3 | D34: BASTONCITOS | E34: Rutina | F34: CCC | G34: Rutina - Baja prioridad (Reposición Automática) | H34: Gris | I34: Izquierda_TERCER Rack | J34: 3 | K34: 3 | L34: 4 | M34: 1 | N34: =16*380/1000 -> 6.08 | O34: =+N34*M34 -> 6.08 | P34: =+$AO$36*O34/SUM($O$27:$O$36) -> 28.174996 | Q34: =25*39.5*23/1000000 -> 0.0227125 | R34: =+N34/Q34 -> 267.694 | S34: 1 | T34: =+$AO$36*S34/SUM($S$27:$S$36) -> 25.019816 | U34: =+Q34*S34 -> 0.0227125 | V34: =25*39.5/10000 -> 0.09875 | W34: =1.37*1.02*0.7/6 -> 0.16303 | X34: 14.21 | Y34: =+V34/X34 -> 0.0069493315 | Z34: =+U34/W34 -> 0.13931485 | AA34: 34.104 | AB34: =+W34/AA34 -> 0.0047803777 | AC34: =+$AN$26*AB34 -> 23.600544 | AD34: =(2.09*2.94*0.75+1.2*1.6*2.09)/AA34*AB34*$AN$26 -> 5.9660506 | AE34: =+AC34+AD34 -> 29.566595 | AF34: =+$AP$26*AE34 -> 9.5500101 | AG34: =+AE34/O34 -> 4.8629268 | AH34: =+AG34*$AP$26 -> 1.5707253 | AI34: =+O34/$O$1048576 -> 0.0014405849
A35: FRIZZIO | B35: CAMARA | C35: 3 | D35: EMPANADAS JAMON Y QUESO / CARNE | E35: Rutina | F35: CCC | G35: Rutina - Baja prioridad (Reposición Automática) | H35: Gris | I35: Izquierda_TERCER Rack | J35: 3 | K35: 3 | L35: 1 | M35: 2 | N35: =18*320/1000 -> 5.76 | O35: =+N35*M35 -> 11.52 | P35: =+$AO$36*O35/SUM($O$27:$O$36) -> 53.384203 | Q35: =51*34.5*14/1000000 -> 0.024633 | R35: =+N35/Q35 -> 233.83266 | S35: 2 | T35: =+$AO$36*S35/SUM($S$27:$S$36) -> 50.039631 | U35: =+Q35*S35 -> 0.049266 | V35: =51*34.5/10000 -> 0.17595 | W35: =1.37*1.02*0.7/6 -> 0.16303 | X35: 14.21 | Y35: =+V35/X35 -> 0.012382125 | Z35: =+U35/W35 -> 0.30218978 | AA35: 34.104 | AB35: =+W35/AA35 -> 0.0047803777 | AC35: =+$AN$26*AB35 -> 23.600544 | AD35: =(2.09*2.94*0.75+1.2*1.6*2.09)/AA35*AB35*$AN$26 -> 5.9660506 | AE35: =+AC35+AD35 -> 29.566595 | AF35: =+$AP$26*AE35 -> 9.5500101 | AG35: =+AE35/O35 -> 2.5665447 | AH35: =+AG35*$AP$26 -> 0.82899393 | AI35: =+O35/$O$1048576 -> 0.0027295292
A36: FROODIE | B36: CAMARA | C36: 3 | D36: FROODIE WRAPS | E36: Rutina | F36: CCC | G36: Rutina - Baja prioridad (Reposición Automática) | H36: Gris | I36: Izquierda_TERCER Rack | J36: 3 | K36: 3 | L36: 6 | M36: 3 | N36: =12*210/1000 -> 2.52 | O36: =+N36*M36 -> 7.56 | P36: =+$AO$36*O36/SUM($O$27:$O$36) -> 35.033383 | Q36: =19*28.5*14/1000000 -> 0.007581 | R36: =+N36/Q36 -> 332.40997 | S36: 3 | T36: =+$AO$36*S36/SUM($S$27:$S$36) -> 75.059447 | U36: =+Q36*S36 -> 0.022743 | V36: =19*28.5/10000 -> 0.05415 | W36: =1.37*1.02*0.7/6 -> 0.16303 | X36: 14.21 | Y36: =+V36/X36 -> 0.0038106967 | Z36: =+U36/W36 -> 0.13950193 | AA36: 34.104 | AB36: =+W36/AA36 -> 0.0047803777 | AC36: =+$AN$26*AB36 -> 23.600544 | AD36: =(2.09*2.94*0.75+1.2*1.6*2.09)/AA36*AB36*$AN$26 -> 5.9660506 | AE36: =+AC36+AD36 -> 29.566595 | AF36: =+$AP$26*AE36 -> 9.5500101 | AG36: =+AE36/O36 -> 3.9109252 | AH36: =+AG36*$AP$26 -> 1.2632288 | AI36: =+O36/$O$1048576 -> 0.0017912536 | AJ36: 0.0294 | AK36: 0.0168 | AL36: =718150542*AK36/1448 -> 8332.1334 | AM36: =+AL36/52 -> 160.23333 | AN36: =74813*AJ36*0.81 -> 1781.5968 | AO36: =+AP36*AN36 -> 575.45576 | AP36: 0.323 | AQ36: =+AO36/AL36 -> 0.069064636
O1048576: =SUM(O2:O1048575) -> 4220.508

Sheet Consumo energia Total Franq
A1: Análisis de Consumo y Costo de Energía Eléctrica — EPEC
A2: Cliente N° 5477641 | Contrato 0102630203 | Figueroa Gallegos Matías Gonzalo | Av. Vélez Sarsfield 3375, Las Flores, Córdoba
A3: Fuente TC: Dólar Oficial Banco Nación (BNA), cotización VENTA, a la fecha de vencimiento de cada factura. Verificado individualmente por fecha (ver notas).
A5: Período | B5: Lectura desde | C5: Lectura hasta | D5: Días | E5: Consumo (kWh) | F5: Total Facturado (ARS) | G5: Fecha TC usado | H5: TC BNA Venta (ARS/USD) | I5: Costo (USD) | J5: Índice Estacional (%) | K5: Precio Promedio (USD/kWh) | M5: Período | N5: Consumo (kWh) | O5: Precio (USD/kWh) | P5: Consumo Acum. (kWh) | Q5: Gasto Acum. (USD)
A6: Ago-Sep 2025 | B6: 2025-08-08 | C6: 2025-09-08 | D6: 31 | E6: 5122 | F6: 1789176.8 | G6: 2025-09-25 | H6: 1355 | I6: 1320.4257 | J6: 82.156844 | K6: 0.25779494 | M6: Ago-Sep 2025 | N6: 5122 | O6: 0.25779494 | P6: 5122 | Q6: 1320.4257
A7: Sep-Oct 2025 | B7: 2025-09-08 | C7: 2025-10-08 | D7: 30 | E7: 6457 | F7: 2305849.4 | G7: 2025-10-28 | H7: 1495 | I7: 1542.3742 | J7: 103.57024 | K7: 0.23886854 | M7: Sep-Oct 2025 | N7: 6457 | O7: 0.23886854 | P7: 11579 | Q7: 2862.7999
A8: Oct-Nov 2025 | B8: 2025-10-08 | C8: 2025-11-10 | D8: 33 | E8: 7492 | F8: 2688749.8 | G8: 2025-12-01 | H8: 1475 | I8: 1822.8812 | J8: 120.17163 | K8: 0.24331036 | M8: Oct-Nov 2025 | N8: 7492 | O8: 0.24331036 | P8: 19071 | Q8: 4685.6811
A9: Nov-Dic 2025 | B9: 2025-11-10 | C9: 2025-12-11 | D9: 31 | E9: 8194 | F9: 2983581.3 | G9: 2025-12-30 | H9: 1480 | I9: 2015.9333 | J9: 131.4317 | K9: 0.24602554 | M9: Nov-Dic 2025 | N9: 8194 | O9: 0.24602554 | P9: 27265 | Q9: 6701.6144
A10: Dic 2025-Ene 2026 | B10: 2025-12-11 | C10: 2026-01-09 | D10: 29 | E10: 8170 | F10: 3002019 | G10: 2026-01-28 | H10: 1463.92 | I10: 2050.6715 | J10: 131.04674 | K10: 0.25100018 | M10: Dic 2025-Ene 2026 | N10: 8170 | O10: 0.25100018 | P10: 35435 | Q10: 8752.2859
A11: Ene-Feb 2026 | B11: 2026-01-09 | C11: 2026-02-11 | D11: 33 | E11: 8708 | F11: 3294776.3 | G11: 2026-03-10 | H11: 1421.51 | I11: 2317.8003 | J11: 139.67626 | K11: 0.26616907 | M11: Ene-Feb 2026 | N11: 8708 | O11: 0.26616907 | P11: 44143 | Q11: 11070.086
A12: Feb-Mar 2026 | B12: 2026-02-11 | C12: 2026-03-09 | D12: 26 | E12: 5936 | F12: 2366687.9 | G12: 2026-04-01 | H12: 1415.79 | I12: 1671.6377 | J12: 95.213399 | K12: 0.28161012 | M12: Feb-Mar 2026 | N12: 5936 | O12: 0.28161012 | P12: 50079 | Q12: 12741.724
A13: Mar-Abr 2026 | B13: 2026-03-09 | C13: 2026-04-09 | D13: 31 | E13: 6564 | F13: 2618064.5 | G13: 2026-04-28 | H13: 1435.68 | I13: 1823.5711 | J13: 105.28651 | K13: 0.27781399 | M13: Mar-Abr 2026 | N13: 6564 | O13: 0.27781399 | P13: 56643 | Q13: 14565.295
A14: Abr-May 2026 | B14: 2026-04-09 | C14: 2026-05-11 | D14: 32 | E14: 5106 | F14: 2138299.7 | G14: 2026-05-28 | H14: 1430.45 | I14: 1494.8441 | J14: 81.900205 | K14: 0.29276225 | M14: Abr-May 2026 | N14: 5106 | O14: 0.29276225 | P14: 61749 | Q14: 16060.139
A15: May-Jun 2026 | B15: 2026-05-11 | C15: 2026-06-10 | D15: 30 | E15: 3781 | F15: 1712871.4 | G15: 2026-06-30 | H15: 1502.09 | I15: 1140.3254 | J15: 60.647214 | K15: 0.3015936 | M15: May-Jun 2026 | N15: 3781 | O15: 0.3015936 | P15: 65530 | Q15: 17200.464
A16: Jun-Jul 2026 | B16: 2026-06-10 | C16: 2026-07-13 | D16: 33 | E16: 4167 | F16: 1956719.2 | G16: 2026-08-03 | H16: 1515 | I16: 1291.5638 | J16: 66.838651 | K16: 0.30995052 | M16: Jun-Jul 2026 | N16: 4167 | O16: 0.30995052 | P16: 69697 | Q16: 18492.028
A17: Jul-Ago 2026 | B17: 2026-07-13 | C17: 2026-08-12 | D17: 30 | E17: 5116 | F17: 2528665.3 | G17: 2026-09-01 | H17: 1530 | I17: 1652.7224 | J17: 82.060604 | K17: 0.32304973 | M17: Jul-Ago 2026 | N17: 5116 | O17: 0.32304973 | P17: 74813 | Q17: 20144.751
A19: TOTAL / PROMEDIO (12 facturas) | E19: 74813 | F19: 29385461 | I19: 20144.751 | J19: 100 | K19: 0.26926805
A22: Notas y fuente de datos:
A23: 1) Consumo (kWh) y Total Facturado (ARS): extraídos directamente de cada factura EPEC (Liquidación de Servicios Públicos), campo 'TOTAL FACTURADO' y 'TOTAL A PAGAR'.
A24: 2) Dataset COMPLETO: las 12 facturas cubren de forma continua Ago 2025 a Ago 2026, sin bimestres parciales (la factura del Bimestre 4/2026 - Liquidación 1 fue incorporada).
A25: 3) Tipo de cambio: Dólar Oficial Banco Nación (BNA), cotización de VENTA, tomado a la fecha de VENCIMIENTO de cada factura. Cada valor fue verificado individualmente contra fuentes de prensa económica argentina (La Nación, El Cronista, Ámbito, Diario de Cuyo) y dolarhistorico.com para la fecha exacta correspondiente al mes y año de cada factura:
A26: • 25/09/2025: $1.355,00 (La Nación, cierre BNA)
A27: • 28/10/2025: $1.495,00 (La Nación, cierre BNA)
A28: • 01/12/2025: $1.475,00 (Diario de Cuyo/Ámbito, cierre BNA)
A29: • 30/12/2025: $1.480,00 (dolarhistorico.com, BNA)
A30: • 28/01/2026: $1.463,92 (dolarhistorico.com, BNA)
A31: • 10/03/2026: $1.421,51 (dolarhistorico.com, BNA)
A32: • 01/04/2026: $1.415,79 (dolarhistorico.com, BNA)
A33: • 28/04/2026: $1.435,68 (dolarhistorico.com, BNA)
... A44: Agrega ambas Liquidaciones de cada Bimestre EPEC. Dataset completo: los 6 bimestres tienen sus 2 liquidaciones.
A46: Bimestre | B46: Liquidaciones incluidas | C46: Estado | D46: Días totales | E46: Consumo total (kWh) | F46: kWh/día | G46: Índice Estacional Bimestral (%)
A47: 5/2025 (Ago-Oct) | B47: Liq. 1 + Liq. 2 | C47: Completo | D47: 61 | E47: 11579 | F47: 189.81967 | G47: 93.574421
A48: 6/2025 (Oct-Dic) | B48: Liq. 1 + Liq. 2 | C48: Completo | D48: 64 | E48: 15686 | F48: 245.09375 | G48: 120.8226
A49: 1/2026 (Dic-Feb) | B49: Liq. 1 + Liq. 2 | C49: Completo | D49: 62 | E49: 16878 | F49: 272.22581 | G49: 134.19775
A50: 2/2026 (Feb-Abr) | B50: Liq. 1 + Liq. 2 | C50: Completo | D50: 57 | E50: 12500 | F50: 219.29825 | G50: 108.10632
A51: 3/2026 (Abr-Jun) | B51: Liq. 1 + Liq. 2 | C51: Completo | D51: 62 | E51: 8887 | F51: 143.33871 | G51: 70.660941
A52: 4/2026 (Jun-Ago) | B52: Liq. 1 + Liq. 2 | C52: Completo | D52: 63 | E52: 9283 | F52: 147.34921 | G52: 72.637975
A54: PROMEDIO kWh/día (6 bimestres) | F54: 202.85423 | G54: 600
A56: Notas:
A57: 1) Índice Estacional Bimestral (%) = (kWh/día del bimestre / promedio de kWh/día de los 6 bimestres) x 100. Se usa kWh/día para comparar bimestres de distinta cantidad de días (57-64 días según el bimestre).
A58: 2) Suma de la columna Índice Estacional Bimestral (%) = 600,00 (6 bimestres x 100), verificación de consistencia.
A59: 3) Los 6 bimestres están completos (2 liquidaciones cada uno) — dataset sin huecos.

Sheet Propuesta Reubicacion en camara
A1: Propuesta de Reubicación — Cámara Grido Vélez Sarsfield (Optimización kWh)
A2: Score = w1×Prioridad_ABC_norm + w2×Eficiencia_energética_norm + w3×Densidad_norm | Pesos ajustables abajo (celdas azules)
A3: Fuente: hoja 'Matriz Layout Camara' (19 SKU, Racks 1-2-3-6 — incluye Tentaciones_1 y Tentaciones_2). Ver notas al pie.
A5: Pesos del score (ajustables): | B5: w1 Prioridad ABC | C5: 0.5 | D5: w2 Eficiencia energética | E5: 0.3 | F5: w3 Densidad kg/m3 | G5: 0.2
A6: Umbrales de zona (score): | B6: Zona 1 (Oro) si Score >= | C6: 0.6 | D6: Zona 2 (Plata) si Score >= | E6: 0.2 | F6: (si no, Zona 3 - Bronce)
A8: Producto | B8: ID_ABC | C8: Ubicación Actual (Rack-Nivel-Pos) | D8: kWh/kg | E8: Kg/m3 bulto | F8: %Util. Volumétrica | G8: USD gasto kWh/posición (año) | H8: Prioridad | I8: Prioridad_norm | J8: Eficiencia_norm | K8: Densidad_norm | L8: SCORE | M8: Zona Propuesta | N8: Ubicación Propuesta
A9: ='Matriz Layout Camara'!D2 -> GRANEL A | B9: ='Matriz Layout Camara'!E2 -> Criticos | C9: ="Rack "&'Matriz Layout Camara'!J2&"-Niv "&'Matriz Layout Camara'!K2&"-Pos "&'Matriz Layout Camara'!L2 -> Rack 1-Niv ND-Pos ND | D9: ='Matriz Layout Camara'!AG2 -> 2.4652499 | E9: ='Matriz Layout Camara'!R2 -> 750 | F9: ='Matriz Layout Camara'!Z2 -> 0.61402214 | G9: ='Matriz Layout Camara'!T2 -> 5871.9976 | H9: =IF(B9="Criticos",3,IF(B9="Estrategicos Financieros",2,1)) -> 3 | I9: =(H9-MIN(H9:H27))/(MAX(H9:H27)-MIN(H9:H27)) -> 1 | J9: =1-(D9-MIN(D9:D27))/(MAX(D9:D27)-MIN(D9:D27)) -> 0.044246039 | K9: =(E9-MIN(E9:E27))/(MAX(E9:E27)-MIN(E9:E27)) -> 1 | L9: =$C$5*I9+$E$5*J9+$G$5*K9 -> 0.71327381 | M9: =IF(L9>=$C$6,"Zona 1 - Oro",IF(L9>=$E$6,"Zona 2 - Plata","Zona 3 - Bronce")) -> Zona 1 - Oro | N9: =IF(ISNUMBER(SEARCH("GRANEL",A9))+ISNUMBER(SEARCH("TENTACIONES",A9)),"Mantener posición (misma) — REDENSIFICAR estibado a >=88% util. volumétrica",IF(ISNUMBER(SEARCH("FAMILIARES",A9)),"Bajar a Nivel 1 — posición dedicada cerca de puerta",IF(M9="Zona 3 - Bronce","Subir a Nivel 2 — consolidar en posición compartida","Mantener en Nivel 1 — posición dedicada"))) -> Mantener posición (misma) — REDENSIFICAR estibado a >=88% util. volumétrica
A10: ='Matriz Layout Camara'!D3 -> GRANEL B | B10: ='Matriz Layout Camara'!E3 -> Criticos | C10: ="Rack "&'Matriz Layout Camara'!J3&"-Niv "&'Matriz Layout Camara'!K3&"-Pos "&'Matriz Layout Camara'!L3 -> Rack 5-Niv ND-Pos ND | D10: ='Matriz Layout Camara'!AG3 -> 2.4041709 | E10: ='Matriz Layout Camara'!R3 -> 750 | F10: ='Matriz Layout Camara'!Z3 -> 0.62962162 | G10: ='Matriz Layout Camara'!T3 -> 4110.3983 | H10: =IF(B10="Criticos",3,IF(B10="Estrategicos Financieros",2,1)) -> 3 | I10: =(H10-MIN(H9:H27))/(MAX(H9:H27)-MIN(H9:H27)) -> 1 | J10: =1-(D10-MIN(D9:D27))/(MAX(D9:D27)-MIN(D9:D27)) -> 0.085727513 | K10: =(E10-MIN(E9:E27))/(MAX(E9:E27)-MIN(E9:E27)) -> 1 | L10: =$C$5*I10+$E$5*J10+$G$5*K10 -> 0.72571825 | M10: =IF(L10>=$C$6,"Zona 1 - Oro",IF(L10>=$E$6,"Zona 2 - Plata","Zona 3 - Bronce")) -> Zona 1 - Oro | N10: =IF(ISNUMBER(SEARCH("GRANEL",A10))+ISNUMBER(SEARCH("TENTACIONES",A10)),"Mantener posición (misma) — REDENSIFICAR estibado a >=88% util. volumétrica",IF(ISNUMBER(SEARCH("FAMILIARES",A10)),"Bajar a Nivel 1 — posición dedicada cerca de puerta",IF(M10="Zona 3 - Bronce","Subir a Nivel 2 — consolidar en posición compartida","Mantener en Nivel 1 — posición dedicada"))) -> Mantener posición (misma) — REDENSIFICAR estibado a >=88% util. volumétrica
A11: ='Matriz Layout Camara'!D4 -> BOMBON ESCOCES | B11: ='Matriz Layout Camara'!E4 -> Criticos | C11: ="Rack "&'Matriz Layout Camara'!J4&"-Niv "&'Matriz Layout Camara'!K4&"-Pos "&'Matriz Layout Camara'!L4 -> Rack 2-Niv 1-Pos 1 | D11: ='Matriz Layout Camara'!AG4 -> 1.7660043 | E11: ='Matriz Layout Camara'!R4 -> 296.00192 | F11: ='Matriz Layout Camara'!Z4 -> 0.85168651 | G11: ='Matriz Layout Camara'!T4 -> 444.8483 | H11: =IF(B11="Criticos",3,IF(B11="Estrategicos Financieros",2,1)) -> 3 | I11: =(H11-MIN(H9:H27))/(MAX(H9:H27)-MIN(H9:H27)) -> 1 | J11: =1-(D11-MIN(D9:D27))/(MAX(D9:D27)-MIN(D9:D27)) -> 0.51913536 | K11: =(E11-MIN(E9:E27))/(MAX(E9:E27)-MIN(E9:E27)) -> 0.084508281 | L11: =$C$5*I11+$E$5*J11+$G$5*K11 -> 0.67264226 | M11: =IF(L11>=$C$6,"Zona 1 - Oro",IF(L11>=$E$6,"Zona 2 - Plata","Zona 3 - Bronce")) -> Zona 1 - Oro | N11: =IF(ISNUMBER(SEARCH("GRANEL",A11))+ISNUMBER(SEARCH("TENTACIONES",A11)),"Mantener posición (misma) — REDENSIFICAR estibado a >=88% util. volumétrica",IF(ISNUMBER(SEARCH("FAMILIARES",A11)),"Bajar a Nivel 1 — posición dedicada cerca de puerta",IF(M11="Zona 3 - Bronce","Subir a Nivel 2 — consolidar en posición compartida","Mantener en Nivel 1 — posición dedicada"))) -> Mantener en Nivel 1 — posición dedicada
A12: ='Matriz Layout Camara'!D5 -> BOMBON SUIZO | B12: ='Matriz Layout Camara'!E5 -> Rutina | C12: ="Rack "&'Matriz Layout Camara'!J5&"-Niv "&'Matriz Layout Camara'!K5&"-Pos "&'Matriz Layout Camara'!L5 -> Rack 2-Niv 1-Pos 6 | D12: ='Matriz Layout Camara'!AG5 -> 2.0705593 | E12: ='Matriz Layout Camara'!R5 -> 287.9729 | F12: ='Matriz Layout Camara'!Z5 -> 0.74666667 | G12: ='Matriz Layout Camara'!T5 -> 177.93932 | H12: =IF(B12="Criticos",3,IF(B12="Estrategicos Financieros",2,1)) -> 1 | I12: =(H12-MIN(H9:H27))/(MAX(H9:H27)-MIN(H9:H27)) -> 0 | J12: =1-(D12-MIN(D9:D27))/(MAX(D9:D27)-MIN(D9:D27)) -> 0.31229826 | K12: =(E12-MIN(E9:E27))/(MAX(E9:E27)-MIN(E9:E27)) -> 0.068317677 | L12: =$C$5*I12+$E$5*J12+$G$5*K12 -> 0.10735301 | M12: =IF(L12>=$C$6,"Zona 1 - Oro",IF(L12>=$E$6,"Zona 2 - Plata","Zona 3 - Bronce")) -> Zona 3 - Bronce | N12: =IF(ISNUMBER(SEARCH("GRANEL",A12))+ISNUMBER(SEARCH("TENTACIONES",A12)),"Mantener posición (misma) — REDENSIFICAR estibado a >=88% util. volumétrica",IF(ISNUMBER(SEARCH("FAMILIARES",A12)),"Bajar a Nivel 1 — posición dedicada cerca de puerta",IF(M12="Zona 3 - Bronce","Subir a Nivel 2 — consolidar en posición compartida","Mantener en Nivel 1 — posición dedicada"))) -> Subir a Nivel 2 — consolidar en posición compartida
A13: ='Matriz Layout Camara'!D6 -> POSTRE CASSATA | B13: ='Matriz Layout Camara'!E6 -> Rutina | C13: ="Rack "&'Matriz Layout Camara'!J6&"-Niv "&'Matriz Layout Camara'!K6&"-Pos "&'Matriz Layout Camara'!L6 -> Rack 2-Niv 1-Pos 5 | D13: ='Matriz Layout Camara'!AG6 -> 2.3466339 | E13: ='Matriz Layout Camara'!R6 -> 254.09373 | F13: ='Matriz Layout Camara'!Z6 -> 0.74666667 | G13: ='Matriz Layout Camara'!T6 -> 177.93932 | H13: =IF(B13="Criticos",3,IF(B13="Estrategicos Financieros",2,1)) -> 1 | I13: =(H13-MIN(H9:H27))/(MAX(H9:H27)-MIN(H9:H27)) -> 0 | J13: =1-(D13-MIN(D9:D27))/(MAX(D9:D27)-MIN(D9:D27)) -> 0.12480351 | K13: =(E13-MIN(E9:E27))/(MAX(E9:E27)-MIN(E9:E27)) -> 0 | L13: =$C$5*I13+$E$5*J13+$G$5*K13 -> 0.037441053 | M13: =IF(L13>=$C$6,"Zona 1 - Oro",IF(L13>=$E$6,"Zona 2 - Plata","Zona 3 - Bronce")) -> Zona 3 - Bronce | N13: =IF(ISNUMBER(SEARCH("GRANEL",A13))+ISNUMBER(SEARCH("TENTACIONES",A13)),"Mantener posición (misma) — REDENSIFICAR estibado a >=88% util. volumétrica",IF(ISNUMBER(SEARCH("FAMILIARES",A13)),"Bajar a Nivel 1 — posición dedicada cerca de puerta",IF(M13="Zona 3 - Bronce","Subir a Nivel 2 — consolidar en posición compartida","Mantener en Nivel 1 — posición dedicada"))) -> Subir a Nivel 2 — consolidar en posición compartida
A14: ='Matriz Layout Camara'!D7 -> POSTRE ALMENDRADO | B14: ='Matriz Layout Camara'!E7 -> Rutina | C14: ="Rack "&'Matriz Layout Camara'!J7&"-Niv "&'Matriz Layout Camara'!K7&"-Pos "&'Matriz Layout Camara'!L7 -> Rack 2-Niv 1-Pos 5 | D14: ='Matriz Layout Camara'!AG7 -> 2.0952088 | E14: ='Matriz Layout Camara'!R7 -> 284.58498 | F14: ='Matriz Layout Camara'!Z7 -> 0.74666667 | G14: ='Matriz Layout Camara'!T7 -> 177.93932 | H14: =IF(B14="Criticos",3,IF(B14="Estrategicos Financieros",2,1)) -> 1 | I14: =(H14-MIN(H9:H27))/(MAX(H9:H27)-MIN(H9:H27)) -> 0 | J14: =1-(D14-MIN(D9:D27))/(MAX(D9:D27)-MIN(D9:D27)) -> 0.29555766 | K14: =(E14-MIN(E9:E27))/(MAX(E9:E27)-MIN(E9:E27)) -> 0.061485909 | L14: =$C$5*I14+$E$5*J14+$G$5*K14 -> 0.10096448 | M14: =IF(L14>=$C$6,"Zona 1 - Oro",IF(L14>=$E$6,"Zona 2 - Plata","Zona 3 - Bronce")) -> Zona 3 - Bronce | N14: =IF(ISNUMBER(SEARCH("GRANEL",A14))+ISNUMBER(SEARCH("TENTACIONES",A14)),"Mantener posición (misma) — REDENSIFICAR estibado a >=88% util. volumétrica",IF(ISNUMBER(SEARCH("FAMILIARES",A14)),"Bajar a Nivel 1 — posición dedicada cerca de puerta",IF(M14="Zona 3 - Bronce","Subir a Nivel 2 — consolidar en posición compartida","Mantener en Nivel 1 — posición dedicada"))) -> Subir a Nivel 2 — consolidar en posición compartida
A15: ='Matriz Layout Camara'!D8 -> BOMBON FRUTEZZA | B15: ='Matriz Layout Camara'!E8 -> Estrategicos Financieros | C15: ="Rack "&'Matriz Layout Camara'!J8&"-Niv "&'Matriz Layout Camara'!K8&"-Pos "&'Matriz Layout Camara'!L8 -> Rack 2-Niv 1-Pos 3 | D15: ='Matriz Layout Camara'!AG8 -> 1.9026761 | E15: ='Matriz Layout Camara'!R8 -> 293.32342 | F15: ='Matriz Layout Camara'!Z8 -> 0.79772727 | G15: ='Matriz Layout Camara'!T8 -> 444.8483 | H15: =IF(B15="Criticos",3,IF(B15="Estrategicos Financieros",2,1)) -> 2 | I15: =(H15-MIN(H9:H27))/(MAX(H9:H27)-MIN(H9:H27)) -> 0.5 | J15: =1-(D15-MIN(D9:D27))/(MAX(D9:D27)-MIN(D9:D27)) -> 0.42631534 | K15: =(E15-MIN(E9:E27))/(MAX(E9:E27)-MIN(E9:E27)) -> 0.079107069 | L15: =$C$5*I15+$E$5*J15+$G$5*K15 -> 0.39371602 | M15: =IF(L15>=$C$6,"Zona 1 - Oro",IF(L15>=$E$6,"Zona 2 - Plata","Zona 3 - Bronce")) -> Zona 2 - Plata | N15: =IF(ISNUMBER(SEARCH("GRANEL",A15))+ISNUMBER(SEARCH("TENTACIONES",A15)),"Mantener posición (misma) — REDENSIFICAR estibado a >=88% util. volumétrica",IF(ISNUMBER(SEARCH("FAMILIARES",A15)),"Bajar a Nivel 1 — posición dedicada cerca de puerta",IF(M15="Zona 3 - Bronce","Subir a Nivel 2 — consolidar en posición compartida","Mantener en Nivel 1 — posición dedicada"))) -> Mantener en Nivel 1 — posición dedicada
A16: ='Matriz Layout Camara'!D9 -> POSTRE CROCANTINO | B16: ='Matriz Layout Camara'!E9 -> Rutina | C16: ="Rack "&'Matriz Layout Camara'!J9&"-Niv "&'Matriz Layout Camara'!K9&"-Pos "&'Matriz Layout Camara'!L9 -> Rack 2-Niv 1-Pos 6 | D16: ='Matriz Layout Camara'!AG9 -> 2.2327054 | E16: ='Matriz Layout Camara'!R9 -> 305.27497 | F16: ='Matriz Layout Camara'!Z9 -> 0.65319588 | G16: ='Matriz Layout Camara'!T9 -> 177.93932 | H16: =IF(B16="Criticos",3,IF(B16="Estrategicos Financieros",2,1)) -> 1 | I16: =(H16-MIN(H9:H27))/(MAX(H9:H27)-MIN(H9:H27)) -> 0 | J16: =1-(D16-MIN(D9:D27))/(MAX(D9:D27)-MIN(D9:D27)) -> 0.20217752 | K16: =(E16-MIN(E9:E27))/(MAX(E9:E27)-MIN(E9:E27)) -> 0.10320749 | L16: =$C$5*I16+$E$5*J16+$G$5*K16 -> 0.081294753 | M16: =IF(L16>=$C$6,"Zona 1 - Oro",IF(L16>=$E$6,"Zona 2 - Plata","Zona 3 - Bronce")) -> Zona 3 - Bronce | N16: =IF(ISNUMBER(SEARCH("GRANEL",A16))+ISNUMBER(SEARCH("TENTACIONES",A16)),"Mantener posición (misma) — REDENSIFICAR estibado a >=88% util. volumétrica",IF(ISNUMBER(SEARCH("FAMILIARES",A16)),"Bajar a Nivel 1 — posición dedicada cerca de puerta",IF(M16="Zona 3 - Bronce","Subir a Nivel 2 — consolidar en posición compartida","Mantener en Nivel 1 — posición dedicada"))) -> Subir a Nivel 2 — consolidar en posición compartida
A17: ='Matriz Layout Camara'!D10 -> POSTRE DELICIA | B17: ='Matriz Layout Camara'!E10 -> Rutina | C17: ="Rack "&'Matriz Layout Camara'!J10&"-Niv "&'Matriz Layout Camara'!K10&"-Pos "&'Matriz Layout Camara'!L10 -> Rack 2-Niv 1-Pos 6 | D17: ='Matriz Layout Camara'!AG10 -> 2.5303995 | E17: ='Matriz Layout Camara'!R10 -> 269.36027 | F17: ='Matriz Layout Camara'!Z10 -> 0.65319588 | G17: ='Matriz Layout Camara'!T10 -> 177.93932 | H17: =IF(B17="Criticos",3,IF(B17="Estrategicos Financieros",2,1)) -> 1 | I17: =(H17-MIN(H9:H27))/(MAX(H9:H27)-MIN(H9:H27)) -> 0 | J17: =1-(D17-MIN(D9:D27))/(MAX(D9:D27)-MIN(D9:D27)) -> 0 | K17: =(E17-MIN(E9:E27))/(MAX(E9:E27)-MIN(E9:E27)) -> 0.030785126 | L17: =$C$5*I17+$E$5*J17+$G$5*K17 -> 0.0061570252 | M17: =IF(L17>=$C$6,"Zona 1 - Oro",IF(L17>=$E$6,"Zona 2 - Plata","Zona 3 - Bronce")) -> Zona 3 - Bronce | N17: =IF(ISNUMBER(SEARCH("GRANEL",A17))+ISNUMBER(SEARCH("TENTACIONES",A17)),"Mantener posición (misma) — REDENSIFICAR estibado a >=88% util. volumétrica",IF(ISNUMBER(SEARCH("FAMILIARES",A17)),"Bajar a Nivel 1 — posición dedicada cerca de puerta",IF(M17="Zona 3 - Bronce","Subir a Nivel 2 — consolidar en posición compartida","Mantener en Nivel 1 — posición dedicada"))) -> Subir a Nivel 2 — consolidar en posición compartida
A18: ='Matriz Layout Camara'!D11 -> BOMBON CROCANTE | B18: ='Matriz Layout Camara'!E11 -> Criticos | C18: ="Rack "&'Matriz Layout Camara'!J11&"-Niv "&'Matriz Layout Camara'!K11&"-Pos "&'Matriz Layout Camara'!L11 -> Rack 2-Niv 1-Pos 2 | D18: ='Matriz Layout Camara'!AG11 -> 1.8285459 | E18: ='Matriz Layout Camara'!R11 -> 277.4681 | F18: ='Matriz Layout Camara'!Z11 -> 0.8775 | G18: ='Matriz Layout Camara'!T11 -> 489.33313 | H18: =IF(B18="Criticos",3,IF(B18="Estrategicos Financieros",2,1)) -> 3 | I18: =(H18-MIN(H9:H27))/(MAX(H9:H27)-MIN(H9:H27)) -> 1 | J18: =1-(D18-MIN(D9:D27))/(MAX(D9:D27)-MIN(D9:D27)) -> 0.47666055 | K18: =(E18-MIN(E9:E27))/(MAX(E9:E27)-MIN(E9:E27)) -> 0.047134656 | L18: =$C$5*I18+$E$5*J18+$G$5*K18 -> 0.65242509 | M18: =IF(L18>=$C$6,"Zona 1 - Oro",IF(L18>=$E$6,"Zona 2 - Plata","Zona 3 - Bronce")) -> Zona 1 - Oro | N18: =IF(ISNUMBER(SEARCH("GRANEL",A18))+ISNUMBER(SEARCH("TENTACIONES",A18)),"Mantener posición (misma) — REDENSIFICAR estibado a >=88% util. volumétrica",IF(ISNUMBER(SEARCH("FAMILIARES",A18)),"Bajar a Nivel 1 — posición dedicada cerca de puerta",IF(M18="Zona 3 - Bronce","Subir a Nivel 2 — consolidar en posición compartida","Mantener en Nivel 1 — posición dedicada"))) -> Mantener en Nivel 1 — posición dedicada
A19: ='Matriz Layout Camara'!D12 -> BOMBON SECRETO | B19: ='Matriz Layout Camara'!E12 -> Estrategicos Financieros | C19: ="Rack "&'Matriz Layout Camara'!J12&"-Niv "&'Matriz Layout Camara'!K12&"-Pos "&'Matriz Layout Camara'!L12 -> Rack 2-Niv 1-Pos 4 | D19: ='Matriz Layout Camara'!AG12 -> 1.8684565 | E19: ='Matriz Layout Camara'!R12 -> 274.09701 | F19: ='Matriz Layout Camara'!Z12 -> 0.86931818 | G19: ='Matriz Layout Camara'!T12 -> 444.8483 | H19: =IF(B19="Criticos",3,IF(B19="Estrategicos Financieros",2,1)) -> 2 | I19: =(H19-MIN(H9:H27))/(MAX(H9:H27)-MIN(H9:H27)) -> 0.5 | J19: =1-(D19-MIN(D9:D27))/(MAX(D9:D27)-MIN(D9:D27)) -> 0.44955542 | K19: =(E19-MIN(E9:E27))/(MAX(E9:E27)-MIN(E9:E27)) -> 0.040336806 | L19: =$C$5*I19+$E$5*J19+$G$5*K19 -> 0.39293399 | M19: =IF(L19>=$C$6,"Zona 1 - Oro",IF(L19>=$E$6,"Zona 2 - Plata","Zona 3 - Bronce")) -> Zona 2 - Plata | N19: =IF(ISNUMBER(SEARCH("GRANEL",A19))+ISNUMBER(SEARCH("TENTACIONES",A19)),"Mantener posición (misma) — REDENSIFICAR estibado a >=88% util. volumétrica",IF(ISNUMBER(SEARCH("FAMILIARES",A19)),"Bajar a Nivel 1 — posición dedicada cerca de puerta",IF(M19="Zona 3 - Bronce","Subir a Nivel 2 — consolidar en posición compartida","Mantener en Nivel 1 — posición dedicada"))) -> Mantener en Nivel 1 — posición dedicada
A20: ='Matriz Layout Camara'!D13 -> FAMILIARES_1 | B20: ='Matriz Layout Camara'!E13 -> Criticos | C20: ="Rack "&'Matriz Layout Camara'!J13&"-Niv "&'Matriz Layout Camara'!K13&"-Pos "&'Matriz Layout Camara'!L13 -> Rack 2-Niv 2-Pos 1 | D20: ='Matriz Layout Camara'!AG13 -> 1.6111423 | E20: ='Matriz Layout Camara'!R13 -> 410.25641 | F20: ='Matriz Layout Camara'!Z13 -> 0.67356077 | G20: ='Matriz Layout Camara'!T13 -> 200.18173 | H20: =IF(B20="Criticos",3,IF(B20="Estrategicos Financieros",2,1)) -> 3 | I20: =(H20-MIN(H9:H27))/(MAX(H9:H27)-MIN(H9:H27)) -> 1 | J20: =1-(D20-MIN(D9:D27))/(MAX(D9:D27)-MIN(D9:D27)) -> 0.62430918 | K20: =(E20-MIN(E9:E27))/(MAX(E9:E27)-MIN(E9:E27)) -> 0.31490362 | L20: =$C$5*I20+$E$5*J20+$G$5*K20 -> 0.75027348 | M20: =IF(L20>=$C$6,"Zona 1 - Oro",IF(L20>=$E$6,"Zona 2 - Plata","Zona 3 - Bronce")) -> Zona 1 - Oro | N20: =IF(ISNUMBER(SEARCH("GRANEL",A20))+ISNUMBER(SEARCH("TENTACIONES",A20)),"Mantener posición (misma) — REDENSIFICAR estibado a >=88% util. volumétrica",IF(ISNUMBER(SEARCH("FAMILIARES",A20)),"Bajar a Nivel 1 — posición dedicada cerca de puerta",IF(M20="Zona 3 - Bronce","Subir a Nivel 2 — consolidar en posición compartida","Mantener en Nivel 1 — posición dedicada"))) -> Bajar a Nivel 1 — posición dedicada cerca de puerta
A21: ='Matriz Layout Camara'!D14 -> FAMILIARES_2 | B21: ='Matriz Layout Camara'!E14 -> Criticos | C21: ="Rack "&'Matriz Layout Camara'!J14&"-Niv "&'Matriz Layout Camara'!K14&"-Pos "&'Matriz Layout Camara'!L14 -> Rack 2-Niv 2-Pos 2 | D21: ='Matriz Layout Camara'!AG14 -> 1.6111423 | E21: ='Matriz Layout Camara'!R14 -> 410.25641 | F21: ='Matriz Layout Camara'!Z14 -> 0.67356077 | G21: ='Matriz Layout Camara'!T14 -> 200.18173 | H21: =IF(B21="Criticos",3,IF(B21="Estrategicos Financieros",2,1)) -> 3 | I21: =(H21-MIN(H9:H27))/(MAX(H9:H27)-MIN(H9:H27)) -> 1 | J21: =1-(D21-MIN(D9:D27))/(MAX(D9:D27)-MIN(D9:D27)) -> 0.62430918 | K21: =(E21-MIN(E9:E27))/(MAX(E9:E27)-MIN(E9:E27)) -> 0.31490362 | L21: =$C$5*I21+$E$5*J21+$G$5*K21 -> 0.75027348 | M21: =IF(L21>=$C$6,"Zona 1 - Oro",IF(L21>=$E$6,"Zona 2 - Plata","Zona 3 - Bronce")) -> Zona 1 - Oro | N21: =IF(ISNUMBER(SEARCH("GRANEL",A21))+ISNUMBER(SEARCH("TENTACIONES",A21)),"Mantener posición (misma) — REDENSIFICAR estibado a >=88% util. volumétrica",IF(ISNUMBER(SEARCH("FAMILIARES",A21)),"Bajar a Nivel 1 — posición dedicada cerca de puerta",IF(M21="Zona 3 - Bronce","Subir a Nivel 2 — consolidar en posición compartida","Mantener en Nivel 1 — posición dedicada"))) -> Bajar a Nivel 1 — posición dedicada cerca de puerta
A22: ='Matriz Layout Camara'!D15 -> FAMILIARES_2 | B22: ='Matriz Layout Camara'!E15 -> Criticos | C22: ="Rack "&'Matriz Layout Camara'!J15&"-Niv "&'Matriz Layout Camara'!K15&"-Pos "&'Matriz Layout Camara'!L15 -> Rack 2-Niv 2-Pos 3 | D22: ='Matriz Layout Camara'!AG15 -> 1.6111423 | E22: ='Matriz Layout Camara'!R15 -> 410.25641 | F22: ='Matriz Layout Camara'!Z15 -> 0.67356077 | G22: ='Matriz Layout Camara'!T15 -> 200.18173 | H22: =IF(B22="Criticos",3,IF(B22="Estrategicos Financieros",2,1)) -> 3 | I22: =(H22-MIN(H9:H27))/(MAX(H9:H27)-MIN(H9:H27)) -> 1 | J22: =1-(D22-MIN(D9:D27))/(MAX(D9:D27)-MIN(D9:D27)) -> 0.62430918 | K22: =(E22-MIN(E9:E27))/(MAX(E9:E27)-MIN(E9:E27)) -> 0.31490362 | L22: =$C$5*I22+$E$5*J22+$G$5*K22 -> 0.75027348 | M22: =IF(L22>=$C$6,"Zona 1 - Oro",IF(L22>=$E$6,"Zona 2 - Plata","Zona 3 - Bronce")) -> Zona 1 - Oro | N22: =IF(ISNUMBER(SEARCH("GRANEL",A22))+ISNUMBER(SEARCH("TENTACIONES",A22)),"Mantener posición (misma) — REDENSIFICAR estibado a >=88% util. volumétrica",IF(ISNUMBER(SEARCH("FAMILIARES",A22)),"Bajar a Nivel 1 — posición dedicada cerca de puerta",IF(M22="Zona 3 - Bronce","Subir a Nivel 2 — consolidar en posición compartida","Mantener en Nivel 1 — posición dedicada"))) -> Bajar a Nivel 1 — posición dedicada cerca de puerta
A23: ='Matriz Layout Camara'!D16 -> FAMILIARES_3 | B23: ='Matriz Layout Camara'!E16 -> Criticos | C23: ="Rack "&'Matriz Layout Camara'!J16&"-Niv "&'Matriz Layout Camara'!K16&"-Pos "&'Matriz Layout Camara'!L16 -> Rack 2-Niv 2-Pos 4 | D23: ='Matriz Layout Camara'!AG16 -> 1.6111423 | E23: ='Matriz Layout Camara'!R16 -> 410.25641 | F23: ='Matriz Layout Camara'!Z16 -> 0.67356077 | G23: ='Matriz Layout Camara'!T16 -> 200.18173 | H23: =IF(B23="Criticos",3,IF(B23="Estrategicos Financieros",2,1)) -> 3 | I23: =(H23-MIN(H9:H27))/(MAX(H9:H27)-MIN(H9:H27)) -> 1 | J23: =1-(D23-MIN(D9:D27))/(MAX(D9:D27)-MIN(D9:D27)) -> 0.62430918 | K23: =(E23-MIN(E9:E27))/(MAX(E9:E27)-MIN(E9:E27)) -> 0.31490362 | L23: =$C$5*I23+$E$5*J23+$G$5*K23 -> 0.75027348 | M23: =IF(L23>=$C$6,"Zona 1 - Oro",IF(L23>=$E$6,"Zona 2 - Plata","Zona 3 - Bronce")) -> Zona 1 - Oro | N23: =IF(ISNUMBER(SEARCH("GRANEL",A23))+ISNUMBER(SEARCH("TENTACIONES",A23)),"Mantener posición (misma) — REDENSIFICAR estibado a >=88% util. volumétrica",IF(ISNUMBER(SEARCH("FAMILIARES",A23)),"Bajar a Nivel 1 — posición dedicada cerca de puerta",IF(M23="Zona 3 - Bronce","Subir a Nivel 2 — consolidar en posición compartida","Mantener en Nivel 1 — posición dedicada"))) -> Bajar a Nivel 1 — posición dedicada cerca de puerta
A24: ='Matriz Layout Camara'!D17 -> FAMILIARES_3 | B24: ='Matriz Layout Camara'!E17 -> Criticos | C24: ="Rack "&'Matriz Layout Camara'!J17&"-Niv "&'Matriz Layout Camara'!K17&"-Pos "&'Matriz Layout Camara'!L17 -> Rack 2-Niv 2-Pos 5 | D24: ='Matriz Layout Camara'!AG17 -> 1.6111423 | E24: ='Matriz Layout Camara'!R17 -> 410.25641 | F24: ='Matriz Layout Camara'!Z17 -> 0.67356077 | G24: ='Matriz Layout Camara'!T17 -> 200.18173 | H24: =IF(B24="Criticos",3,IF(B24="Estrategicos Financieros",2,1)) -> 3 | I24: =(H24-MIN(H9:H27))/(MAX(H9:H27)-MIN(H9:H27)) -> 1 | J24: =1-(D24-MIN(D9:D27))/(MAX(D9:D27)-MIN(D9:D27)) -> 0.62430918 | K24: =(E24-MIN(E9:E27))/(MAX(E9:E27)-MIN(E9:E27)) -> 0.31490362 | L24: =$C$5*I24+$E$5*J24+$G$5*K24 -> 0.75027348 | M24: =IF(L24>=$C$6,"Zona 1 - Oro",IF(L24>=$E$6,"Zona 2 - Plata","Zona 3 - Bronce")) -> Zona 1 - Oro | N24: =IF(ISNUMBER(SEARCH("GRANEL",A24))+ISNUMBER(SEARCH("TENTACIONES",A24)),"Mantener posición (misma) — REDENSIFICAR estibado a >=88% util. volumétrica",IF(ISNUMBER(SEARCH("FAMILIARES",A24)),"Bajar a Nivel 1 — posición dedicada cerca de puerta",IF(M24="Zona 3 - Bronce","Subir a Nivel 2 — consolidar en posición compartida","Mantener en Nivel 1 — posición dedicada"))) -> Bajar a Nivel 1 — posición dedicada cerca de puerta
A25: ='Matriz Layout Camara'!D18 -> FAMILIARES_4 | B25: ='Matriz Layout Camara'!E18 -> Criticos | C25: ="Rack "&'Matriz Layout Camara'!J18&"-Niv "&'Matriz Layout Camara'!K18&"-Pos "&'Matriz Layout Camara'!L18 -> Rack 2-Niv 2-Pos 6 | D25: ='Matriz Layout Camara'!AG18 -> 1.6111423 | E25: ='Matriz Layout Camara'!R18 -> 410.25641 | F25: ='Matriz Layout Camara'!Z18 -> 0.67356077 | G25: ='Matriz Layout Camara'!T18 -> 200.18173 | H25: =IF(B25="Criticos",3,IF(B25="Estrategicos Financieros",2,1)) -> 3 | I25: =(H25-MIN(H9:H27))/(MAX(H9:H27)-MIN(H9:H27)) -> 1 | J25: =1-(D25-MIN(D9:D27))/(MAX(D9:D27)-MIN(D9:D27)) -> 0.62430918 | K25: =(E25-MIN(E9:E27))/(MAX(E9:E27)-MIN(E9:E27)) -> 0.31490362 | L25: =$C$5*I25+$E$5*J25+$G$5*K25 -> 0.75027348 | M25: =IF(L25>=$C$6,"Zona 1 - Oro",IF(L25>=$E$6,"Zona 2 - Plata","Zona 3 - Bronce")) -> Zona 1 - Oro | N25: =IF(ISNUMBER(SEARCH("GRANEL",A25))+ISNUMBER(SEARCH("TENTACIONES",A25)),"Mantener posición (misma) — REDENSIFICAR estibado a >=88% util. volumétrica",IF(ISNUMBER(SEARCH("FAMILIARES",A25)),"Bajar a Nivel 1 — posición dedicada cerca de puerta",IF(M25="Zona 3 - Bronce","Subir a Nivel 2 — consolidar en posición compartida","Mantener en Nivel 1 — posición dedicada"))) -> Bajar a Nivel 1 — posición dedicada cerca de puerta
A26: ='Matriz Layout Camara'!D19 -> TENTACIONES_1 (Dulce de Leche Granizado/Chocolate con Almendras/Limon/Granizado/Cookie) | B26: ='Matriz Layout Camara'!E19 -> Criticos | C26: ="Rack "&'Matriz Layout Camara'!J19&"-Niv "&'Matriz Layout Camara'!K19&"-Pos "&'Matriz Layout Camara'!L19 -> Rack 3-Niv 1-Pos 6 | D26: ='Matriz Layout Camara'!AG19 -> 1.410614 | E26: ='Matriz Layout Camara'!R19 -> 387.18728 | F26: ='Matriz Layout Camara'!Z19 -> 0.35744266 | G26: ='Matriz Layout Camara'!T19 -> 735.67741 | H26: =IF(B26="Criticos",3,IF(B26="Estrategicos Financieros",2,1)) -> 3 | I26: =(H26-MIN(H9:H27))/(MAX(H9:H27)-MIN(H9:H27)) -> 1 | J26: =1-(D26-MIN(D9:D27))/(MAX(D9:D27)-MIN(D9:D27)) -> 0.76049703 | K26: =(E26-MIN(E9:E27))/(MAX(E9:E27)-MIN(E9:E27)) -> 0.26838449 | L26: =$C$5*I26+$E$5*J26+$G$5*K26 -> 0.78182601 | M26: =IF(L26>=$C$6,"Zona 1 - Oro",IF(L26>=$E$6,"Zona 2 - Plata","Zona 3 - Bronce")) -> Zona 1 - Oro | N26: =IF(ISNUMBER(SEARCH("GRANEL",A26))+ISNUMBER(SEARCH("TENTACIONES",A26)),"Mantener posición (misma) — REDENSIFICAR estibado a >=88% util. volumétrica",IF(ISNUMBER(SEARCH("FAMILIARES",A26)),"Bajar a Nivel 1 — posición dedicada cerca de puerta",IF(M26="Zona 3 - Bronce","Subir a Nivel 2 — consolidar en posición compartida","Mantener en Nivel 1 — posición dedicada"))) -> Mantener posición (misma) — REDENSIFICAR estibado a >=88% util. volumétrica
A27: ='Matriz Layout Camara'!D20 -> TENTACIONES_2 (Toddy galletitas/Frutilla/Crema Americana/Chocolate/Menta Granizada/Vainilla/Cadbury y Cocolate con Almendras) | B27: ='Matriz Layout Camara'!E20 -> Rutina | C27: ="Rack "&'Matriz Layout Camara'!J20&"-Niv "&'Matriz Layout Camara'!K20&"-Pos "&'Matriz Layout Camara'!L20 -> Rack 3-Niv 2-Pos 6 | D27: ='Matriz Layout Camara'!AG20 -> 1.0579605 | E27: ='Matriz Layout Camara'!R20 -> 387.18728 | F27: ='Matriz Layout Camara'!Z20 -> 0.47659021 | G27: ='Matriz Layout Camara'!T20 -> 980.90321 | H27: =IF(B27="Criticos",3,IF(B27="Estrategicos Financieros",2,1)) -> 1 | I27: =(H27-MIN(H9:H27))/(MAX(H9:H27)-MIN(H9:H27)) -> 0 | J27: =1-(D27-MIN(D9:D27))/(MAX(D9:D27)-MIN(D9:D27)) -> 1 | K27: =(E27-MIN(E9:E27))/(MAX(E9:E27)-MIN(E9:E27)) -> 0.26838449 | L27: =$C$5*I27+$E$5*J27+$G$5*K27 -> 0.3536769 | M27: =IF(L27>=$C$6,"Zona 1 - Oro",IF(L27>=$E$6,"Zona 2 - Plata","Zona 3 - Bronce")) -> Zona 2 - Plata | N27: =IF(ISNUMBER(SEARCH("GRANEL",A27))+ISNUMBER(SEARCH("TENTACIONES",A27)),"Mantener posición (misma) — REDENSIFICAR estibado a >=88% util. volumétrica",IF(ISNUMBER(SEARCH("FAMILIARES",A27)),"Bajar a Nivel 1 — posición dedicada cerca de puerta",IF(M27="Zona 3 - Bronce","Subir a Nivel 2 — consolidar en posición compartida","Mantener en Nivel 1 — posición dedicada"))) -> Mantener posición (misma) — REDENSIFICAR estibado a >=88% util. volumétrica
A30: Diagnóstico y Ahorro Estimado
A31: Costo energético total cámara (USD/año, prorrateado) | D31: =SUM(G9:G27) -> 15613.642
A32: Costo GRANEL A+B y TENTACIONES 1+2 (USD/año) | D32: =SUMIF(A9:A27,"GRANEL A",G9:G27)+SUMIF(A9:A27,"GRANEL B",G9:G27)+SUMPRODUCT(ISNUMBER(SEARCH("TENTACIONES",A9:A27))*G9:G27) -> 11698.976
A33: % del gasto total de la cámara que representan estos 4 ítems a granel | D33: =D32/D31 -> 0.74927918
A34: %Util. volumétrica promedio actual (4 ítems a granel) | D34: =AVERAGE(SUMIF(A9:A27,"GRANEL A",F9:F27),SUMIF(A9:A27,"GRANEL B",F9:F27),SUMPRODUCT(ISNUMBER(SEARCH("TENTACIONES_1",A9:A27))*F9:F27),SUMPRODUCT(ISNUMBER(SEARCH("TENTACIONES_2",A9:A27))*F9:F27)) -> 0.51941916
A35: Objetivo de %Util. volumétrica tras redensificación (supuesto, editable) | D35: 0.88
A36: Rango de reducción de costo estimado (supuesto conservador, editable) | C36: Mínimo | D36: 0.05 | E36: Máximo | F36: 0.1 | G36: Promedio Ahorro usd
A37: AHORRO ANUAL ESTIMADO (USD) — redensificación de los 4 ítems a granel | C37: Mínimo | D37: =D32*D36 -> 584.94882 | E37: Máximo | F37: =D32*F36 -> 1169.8976 | G37: =+(D37+F37)/2 -> 877.42323 | H37: Monto "piso2 o de minima estimado de ahorro anual
A40: Costo Energético por Zona Propuesta
A41: Zona | B41: Costo USD/año | C41: Cantidad SKU-posiciones
A42: Zona 1 - Oro | B42: =SUMIF($M$9:$M$27,A42,$G$9:$G$27) -> 12853.345 | C42: =COUNTIF($M$9:$M$27,A42) -> 11
A43: Zona 2 - Plata | B43: =SUMIF($M$9:$M$27,A43,$G$9:$G$27) -> 1870.5998 | C43: =COUNTIF($M$9:$M$27,A43) -> 3
A44: Zona 3 - Bronce | B44: =SUMIF($M$9:$M$27,A44,$G$9:$G$27) -> 889.6966 | C44: =COUNTIF($M$9:$M$27,A44) -> 5
A47: Notas y supuestos:
A48: 1) Prioridad ABC: Críticos=3, Estratégicos Financieros=2, Rutina=1 (según columna ID_ABC de 'Matriz Layout Camara').
A49: 2) Score y Zona recalculan automáticamente si se cambian los pesos (C5,E5,G5) o los umbrales (C6,E6) — celdas azules.
A50: 3) El objetivo de %Util. Volumétrica se elevó de 78% a 88% al incorporar Tentaciones: al confirmarse que Granel es de base rectangular (sin límite geométrico de empaquetado circular), 88% es un techo razonable dejando margen para circulación de aire. Se asume el mismo formato rectangular para Tentaciones — a confirmar en piso.
A51: 4) El ahorro estimado es una proyección conservadora basada en la mejora de %Util. volumétrica; asume que ese componente explica proporcionalmente parte del consumo prorrateado (no el 100%). Ajustable en las celdas azules D37:F38.
A52: 5) ALERTA DE DATOS: para 3 SKU (Granel B, Familiares_4, Tentaciones_2) la matriz trae costo energético REAL medido, distinto del prorrateado: Granel B mide USD 9.982/año vs. USD 4.110 del modelo (2,4x más). No se extrapola esa proporción a los demás ítems por falta de dato medido — se recomienda instrumentar medición real antes de fijar presupuesto definitivo.
A53: 6) El intercambio Nivel 1 <-> Nivel 2 y la consolidación de posiciones compartidas en Rack 2 NO están cuantificados en USD (el prorrateo se basa en m3, no en nivel/altura ni frecuencia de apertura de puerta) — es recomendación cualitativa de buenas prácticas de cadena de frío.
A54: 7) HALLAZGO ESTRUCTURAL: Tentaciones_1 es Crítico (alta rotación) pero está en el Rack 3, el más alejado de la puerta de los 4 racks. Corregirlo requiere mover racks físicos de lugar — excede el alcance de la re-eslotización de producto y se deja para evaluación de layout de sala.
A55: 8) Análisis acotado a los 19 SKU-posición y Racks 1, 2, 3 y 6 de la matriz.

Sheet Caso de Negocio 
A1: CASO DE NEGOCIO — Optimización Energética de Cámara de Frío
A2: Grido Vélez Sarsfield | Presentación a Directorio | Racks 1-2-3-6, 19 SKU-posición
A4: Concentración del gasto energético en 4 SKU a granel | C4: Ahorro anual estimado (rango conservador) | E4: Venta equivalente (al ratio de 0,05 USD/USD) | G4: SKU que NO requieren mover de posición
A6: ='Propuesta Reubicacion en camara'!D33 -> 0.74927918 | C6: ="USD "&TEXT(G25,"#,##0")&" - "&TEXT(H25,"#,##0") -> USD 654 - 982 | E6: ="USD "&TEXT(G25/D12,"#,##0")&" - "&TEXT(H25/D12,"#,##0") -> USD 13,087 - 19,630 | G6: 8 de 17 (47%)
A10: Supuestos y racional del cálculo (editables — celdas azules)
A11: Precio de energía (USD/kWh) — validado contra la matriz y la última factura EPEC real | D11: 0.323
A12: USD de energía por cada USD vendido (ratio de conversión a venta equivalente) | D12: 0.05
A13: % del costo de una posición atribuible a infiltración de aire por apertura de puerta (mínimo) — supuesto de ingeniería, ajustable | D13: 0.08
A14: % del costo de una posición atribuible a infiltración de aire por apertura de puerta (máximo) — supuesto de ingeniería, ajustable | D14: 0.12
A15: %Util. Volumétrica objetivo tras redensificación (dato: viene de 'Propuesta Reubicacion en camara') | D15: ='Propuesta Reubicacion en camara'!D35 -> 0.88
A17: Ahorro Estimado por Producto — Racional: Reducción de Infiltración de Aire por Apertura de Puerta
A18: Mecanismo causal: el producto sólido desplaza aire; menos aire libre en la posición = menos aire caliente ingresa en cada apertura de puerta = menos ciclado del compresor.
A20: Producto | B20: Costo Asignado (USD/año) | C20: %Util. Actual | D20: %Aire Actual | E20: %Aire Objetivo | F20: Reducción de Aire Desperdiciado | G20: Ahorro Mínimo (5% del costo es aire) | H20: Ahorro Máximo (10% del costo es aire)
A21: GRANEL A | B21: ='Propuesta Reubicacion en camara'!G9 -> 5871.9976 | C21: ='Propuesta Reubicacion en camara'!F9 -> 0.61402214 | D21: =1-C21 -> 0.38597786 | E21: =1-$D$15 -> 0.12 | F21: =(D21-E21)/D21 -> 0.68910134 | G21: =B21*$D$13*F21 -> 323.71211 | H21: =B21*$D$14*F21 -> 485.56817
A22: GRANEL B | B22: ='Propuesta Reubicacion en camara'!G10 -> 4110.3983 | C22: ='Propuesta Reubicacion en camara'!F10 -> 0.62962162 | D22: =1-C22 -> 0.37037838 | E22: =1-$D$15 -> 0.12 | F22: =(D22-E22)/D22 -> 0.67600701 | G22: =B22*$D$13*F22 -> 222.29264 | H22: =B22*$D$14*F22 -> 333.43896
A23: TENTACIONES_1 | B23: ='Propuesta Reubicacion en camara'!G26 -> 735.67741 | C23: ='Propuesta Reubicacion en camara'!F26 -> 0.35744266 | D23: =1-C23 -> 0.64255734 | E23: =1-$D$15 -> 0.12 | F23: =(D23-E23)/D23 -> 0.81324624 | G23: =B23*$D$13*F23 -> 47.862951 | H23: =B23*$D$14*F23 -> 71.794426
A24: TENTACIONES_2 | B24: ='Propuesta Reubicacion en camara'!G27 -> 980.90321 | C24: ='Propuesta Reubicacion en camara'!F27 -> 0.47659021 | D24: =1-C24 -> 0.52340979 | E24: =1-$D$15 -> 0.12 | F24: =(D24-E24)/D24 -> 0.77073413 | G24: =B24*$D$13*F24 -> 60.481247 | H24: =B24*$D$14*F24 -> 90.72187 | I24: Ahorro promedio
A25: TOTAL | B25: =SUM(B21:B24) -> 11698.976 | G25: =SUM(G21:G24) -> 654.34895 | H25: =SUM(H21:H24) -> 981.52343 | I25: =(G25+H25)/2 -> 817.93619
A26: ⚠ Alerta de Rigor de Datos — Costo Real Medido vs. Modelo Prorrateado
A27: Producto | B27: Costo Prorrateado (USD/año) | C27: Costo Real Medido (USD/año) | D27: Factor (Real / Modelo)
A28: GRANEL B | B28: 4110.4 | C28: 9982.4 | D28: =C28/B28 -> 2.4285714
A29: FAMILIARES_4 | B29: 200.18 | C29: 3914.67 | D29: =C29/B29 -> 19.55575
A30: TENTACIONES_2 | B30: 980.9 | C30: 1716.58 | D30: =C30/B30 -> 1.7500051
A32: Para estos 3 SKU la matriz trae el consumo REAL medido (no solo el modelo prorrateado por m3). El costo real es entre 1,7x y 19,6x mayor que la estimación del modelo. No extrapolamos esta proporción a Granel A y Tentaciones_1 por falta de dato medido — pero si el patrón se repite, el ahorro real podría superar ampliamente los USD 654-982 estimados arriba. Recomendación: instrumentar medición real de los 4 ítems a granel antes de fijar el presupuesto definitivo de ahorro.
A36: Recomendaciones al Directorio
A37: 1) APROBAR la redensificación del estibado de Granel A, Granel B, Tentaciones_1 y Tentaciones_2 — bajo capex (cambio de método, no de infraestructura). Ahorro estimado USD 1.635-2.453/año, por reducción de infiltración de aire en cada apertura de puerta (ver racional y supuestos explícitos en la tabla de arriba).
A38: 2) APROBAR el re-eslotizado interno del Rack 2 (7 SKU cambian de nivel) — costo cero, mejora de estabilidad térmica y reduce tiempo de puerta abierta en los productos de mayor rotación.
A39: 3) INSTRUMENTAR medición real de consumo en los 4 ítems a granel antes del cierre de presupuesto — el ahorro real podría ser mayor al estimado conservador.
A40: 4) EVALUAR (fuera de este análisis) el intercambio físico de posición entre Rack 2 y Rack 3 — Tentaciones_1 es un producto Crítico ubicado hoy en el rack más lejano de la puerta.

Sheet Diferencias
A1: Diferencias entre Ubicación Actual vs. Propuesta — Por SKU
A3: Trabajo a nivel de SKU único (17 productos; Familiares_2 y Familiares_3 ocupan 2 posiciones físicas cada uno, Tentaciones_1 y Tentaciones_2 incorporados).
A5: SKU | B5: Zona | C5: Ubicación Actual | D5: Ubicación Propuesta | E5: Tipo de Cambio | F5: Motivo
A6: GRANEL A | B6: 🥇 Oro | C6: Rack 1 - Niv ND - Pos ND | D6: Rack 1 - Niv ND - Pos ND | E6: Sin cambio de posición — cambia el método | F6: Ya está en el lugar correcto (frente); el problema es la compactación del estibado, no la ubicación
A7: GRANEL B | B7: 🥇 Oro | C7: Rack 6 - Niv ND - Pos ND | D7: Rack 6 - Niv ND - Pos ND | E7: Sin cambio de posición — cambia el método | F7: Ídem GRANEL A
A8: BOMBON ESCOCES | B8: 🥇 Oro | C8: Rack 2 - Niv 1 - Pos 1 | D8: Rack 2 - Niv 1 - Pos 1 | E8: Sin cambio | F8: Ya es el benchmark de eficiencia del rack (85,2% util. volumétrica)
A9: BOMBON CROCANTE | B9: 🥇 Oro | C9: Rack 2 - Niv 1 - Pos 2 | D9: Rack 2 - Niv 1 - Pos 2 | E9: Sin cambio | F9: Ídem — 87,8% util. volumétrica, el mejor de toda la cámara
A10: FAMILIARES_1 | B10: 🥇 Oro | C10: Rack 2 - Niv 2 - Pos 1 | D10: Rack 2 - Niv 1 - Pos 5 | E10: ⬇️ Baja de nivel | F10: Alta prioridad mejor eficiencia (1,19 kWh/kg) — merece el nivel más frío/estable y de acceso directo
A11: FAMILIARES_4 | B11: 🥇 Oro | C11: Rack 2 - Niv 2 - Pos 6 | D11: Rack 2 - Niv 1 - Pos 6 | E11: ⬇️ Baja de nivel | F11: Ídem FAMILIARES_1
A12: FAMILIARES_2 | B12: 🥇 Oro | C12: Rack 2 - Niv 2 - Pos 2 y 3 | D12: Rack 2 - Niv 2 - Pos 1 y 2 | E12: 🔄 Reordenado (mismo nivel) | F12: Se corre para ceder Pos 1 a las que bajan a Nivel 1; sigue arriba por su huella de 2 posiciones
A13: FAMILIARES_3 | B13: 🥇 Oro | C13: Rack 2 - Niv 2 - Pos 4 y 5 | D13: Rack 2 - Niv 2 - Pos 3 y 4 | E13: 🔄 Reordenado (mismo nivel) | F13: Ídem FAMILIARES_2
A14: BOMBON FRUTEZZA | B14: 🥈 Plata | C14: Rack 2 - Niv 1 - Pos 3 | D14: Rack 2 - Niv 1 - Pos 3 | E14: Sin cambio | F14: Buen margen (Estratégico), mantiene visibilidad en Nivel 1
A15: BOMBON SECRETO | B15: 🥈 Plata | C15: Rack 2 - Niv 1 - Pos 4 | D15: Rack 2 - Niv 1 - Pos 4 | E15: Sin cambio | F15: Ídem BOMBON FRUTEZZA
A16: BOMBON SUIZO | B16: 🥉 Bronce | C16: Rack 2 - Niv 1 - Pos 6 (compartida c/ 2 más) | D16: Rack 2 - Niv 2 - Pos 5 (dedicada) | E16: ⬆️ Sube de nivel | F16: Baja rotación — libera Nivel 1 y de paso pasa a tener posición propia (antes compartía con 2 SKU)
... A22: TENTACIONES_2 | B22: 🥈 Plata | C22: Rack 3 - Niv 2 - Pos 6 | D22: Rack 3 - Niv 2 - Pos 6 | E22: Sin cambio de posición — cambia el método | F22: 47,7% util. volumétrica; baja rotación confirmada (8,8% kg vendido/año) — redensificar igual que Granel
A24: Resumen del movimiento
A26: Tipo de cambio | B26: Cantidad SKU | C26: % del total
A27: Sin cambio de posición (Granel + Tentaciones cambian método) | B27: 8 | C27: 0.47
A28: Reordenado dentro del mismo nivel | B28: 2 | C28: 0.12
A29: Baja de Nivel 2 → Nivel 1 | B29: 2 | C29: 0.12
A30: Sube de Nivel 1 → Nivel 2 | B30: 5 | C30: 0.29
A32: Lectura clave: el 47% de los SKU (Escoces, Crocante, Frutezza, Secreto, ambos Granel y ambas Tentaciones) no cambian de posición física — ya estaban bien puestos o no admiten reubicación (formato a granel de posición única). El movimiento real es un intercambio de 7 SKU entre niveles dentro del Rack 2 (2 Familiares bajan, 5 Rutina suben), más la consolidación de los 4 postres de menor rotación en una sola posición compartida. Adicionalmente, los 4 ítems a granel (Granel A/B, Tentaciones 1/2) concentran el 74,9% del gasto energético de la cámara y son el foco prioritario de ahorro por método de estibado, no por reubicación.

Sheet Layout producto en camara
B2: Situacion actual | C2: Situacion propuesta
B19: Referencia de Códigos
B20: F1, F2, F3, F4 | C20: Familiares 1 a 4
B21: ESC | C21: Bombón Escocés
B22: CRO | C22: Bombón Crocante
B23: FRU | C23: Bombón Frutezza
B24: SEC | C24: Bombón Secreto
B25: SUI | C25: Bombón Suizo
B26: CAS | C26: Postre Cassata
B27: ALM | C27: Postre Almendrado
B28: CRI | C28: Postre Crocantino
B29: DEL | C29: Postre Delicia
B30: T1 | C30: Tentaciones_1 (Dulce de Leche Granizado/Choc. con Almendras/Limón/Granizado/Cookie)
B31: T2 | C31: Tentaciones_2 (Toddy galletitas/Frutilla/Crema Americana/Chocolate/Menta Granizada/Vainilla/Cadbury y Choc. con Almendras)
B33: Cómo leer el sketch:
B34: • Color de la celda = prioridad ABC (Verde=Críticos, Amarillos =Estratégico Financiero, gris=Rutina). Granel y Tentaciones en teal (formato a granel).
B35: • Dentro de Granel A/B y Tentaciones: la franja celeste es AIRE (espacio pagado y sin producto); la franja teal es producto real. El % es la Utilización Volumétrica.
B36: • En la Propuesta, Familiares (F1,F4) bajan a Nivel 1 y los productos de Rutina (SUI, CAS, ALM, CRI, DEL) suben a Nivel 2 y se consolidan.

Sheet Memoria de calculo del ahorro
A2: 1. Ecuación Base del Modelo Termodinámico
A3: El ahorro anual por posición (A) se calcula mediante el producto del Gasto Energético Actual (C) multiplicado por el Factor de Mejora de Eficiencia (Ef):
A5: Ahorro (A) = Gasto Actual (C) x Factor de Eficiencia (Ef)
A7: Definición de Factores de Eficiencia (Ef):
A8: • Estrato Base (Niveles 1 y 2): Ef = 0.05 (5% de ahorro). Derivado de la mejora del tiro perimetral del aire y estabilización de la masa térmica.
A9: • Estrato Superior (Nivel 3): Ef = 0.10 (10% de ahorro). Derivado de la eliminación del sobre-enfriamiento innecesario en productos fraccionados y livianos.
A11: 2. Desglose Analítico por Producto
A13: Grupo A: Productos reubicados en Niveles 1 y 2 (Eficiencia = 5%)
A14: Artículos de alta masa térmica ("anclas térmicas") y productos críticos de alta rotación (AAA/ABB).
A16: • GRANEL A:
A17: Ahorro = USD 5,871.99 x 0.05 = USD 293.60
A19: • GRANEL B:
... A132: . El Origen Real: Heurística y Rangos Típicos de Auditoría
C133: El eje horizontal (X) representa el porcentaje de reducción de resistencia aerodinámica que obtiene el sistema de refrigeración cuando se
A134: En la práctica de la consultoría de operaciones logísticas de frío, cuando no se dispone de data logger diferencial instalado, se utilizan factores de corrección estándar por buenas prácticas de layout validados en bibliografía de optimización de almacenes refrigerados. | C134: reordenan las posiciones de almacenamiento dentro de la cámara
C135: este eje mide el grado de "alivio" en la circulación del aire frío al eliminar la congestión física en los racks.
A136: Los rangos habituales de mejora energética al corregir la congestión de flujos de aire en estanterías selectivas rondan:
C137: Desglose del Eje X:= Delta P(estática)/Delta P_(nominal) en (%)
C139: Presión Estática Nominal P(nominal):
A140: Entre el 3% y el 6% para zonas de baja fricción y acumulación de masa (adoptado conservadoramente como 5%).
C141: Es la contrapresión de diseño que deben vencer los ventiladores de los evaporadores para impulsar el aire frío a través de toda la cámara cuando está llena de productos.
A142: Entre el 8% y el 12% para zonas de eliminación de corrientes parásitas superiores (adoptado conservadoramente como 10%). | C142: Variación de Presión Estática ($\Delta P_{\text{estática}}$):
C145: Es la fricción aerodinámica que se elimina al despejar el perímetro de circulación y remover los bloques de picking masivo de las zonas de flujo crítico.
C148: Valor Porcentual del Eje X (0% a 20%):
C149: Cuantifica qué porcentaje del "esfuerzo de soplado" de los ventiladores se ha liberado gracias al nuevo layout.
C151: Ejemplo breve
C152: El caso de un filtro de aire obstruido:
C153: Si un motor intenta aspirar aire a través de un filtro tapado, requiere mayor potencia para vencer la resistencia. Al limpiar el filtro, la contrapresión disminuye y el motor trabaja descansado.
C154: En la cámara ocurre exactamente lo mismo: los pallets mal ubicados actúan como el "filtro obstruido". El eje X indica qué porcentaje de esa obstrucción logramos remover.
C156: Justificación de Valor para el Cliente y la Auditoría
C157: Posicionamiento en el punto X= 0%: Al no disponer de manómetros diferenciales instalados en los ductos para medir la caída de presión exacta en milímetros de columna de agua,
F158: la consultoría adopta la postura prudente de ubicarse en el origen, X=0% de mejora aerodinámica medida).
C160: Garantía de Resultados: Al fijar el modelo en el punto inicial x= 0%, los coeficientes de ahorro asignados , 5% en base y 10% en techo constituyen el piso técnico mínimo garantizado.
E161: Cualquier mejora aerodinámica real que ocurra en la práctica desplazará la operación hacia la derecha del eje X, aumentando el ahorro económico por encima del proyectado.
